{
    "1489436418097,042ecf32-dbf3-4eb8-8b6f-58a5109de3e0": {
        "domain": "", 
        "dst_ip": "52.1.42.145", 
        "dst_port": 443, 
        "headers": {
            "accept": "application/json", 
            "accept-encoding": "gzip", 
            "connection": "Keep-Alive", 
            "content-length": "857", 
            "content-type": "application/json", 
            "host": "live.chartboost.com", 
            "user-agent": "Dalvik/2.1.0 (Linux; U; Android 7.0; Nexus 6 Build/NBD91Y)", 
            "x-chartboost-api": "6.4.2", 
            "x-chartboost-app": "57ac96abf6cd450a53bd8003", 
            "x-chartboost-client": "Chartboost-Android-SDK Unity 6.4.2", 
            "x-chartboost-signature": "43f83c9ada62d9f4a2c5d8df8d4ab98ba8af92a4"
        }, 
        "host": "live.chartboost.com", 
        "is_foreground": true, 
        "is_host_ip": 0, 
        "label": 0, 
        "md5": null, 
        "method": "POST", 
        "package_name": "com.motionvolt.flipdiving", 
        "package_version": "2.6.7", 
        "pii_types": null, 
        "platform": "android", 
        "post_body": "[{\"tracking\":0,\"device_type\":\"motorola Nexus 6\",\"sdk\":\"6.4.2\",\"dpi\":\"560\",\"carrier\":{\"phone-type\":1,\"carrier-name\":\"T-Mobile\",\"iso-country-code\":\"us\",\"mobile-country-code\":\"202\",\"mobile-network-code\":\"01\"},\"timestamp\":\"1489436417\",\"identity\":\"eyJ1dWlkIjoiNDZkZjc5MDBhYTYyNzQzZiIsIm1hY2lkIjoiMmY1NjcyY2I3NjY5MWI5ODliYmQy\\nMDIyYTUzNDk5MzlhMmQ3Yjk1MiIsImdhaWQiOiJjN2JhYmY4ODdiODQ0NWM2YjQzNDA1NjE4N2Q4\\nNTg3MyJ9\\n\",\"rooted_device\":false,\"bundle\":\"2.6.7\",\"dh\":\"2392\",\"scale\":\"3.5\",\"dw\":\"1440\",\"session\":1,\"mobile_network\":13,\"framework_version\":\"6.4.5\",\"app\":\"57ac96abf6cd450a53bd8003\",\"h\":\"2392\",\"os\":\"Android 7.0\",\"timezone\":\"GMT-07:00\",\"w\":\"1440\",\"commit_hash\":\"b9500dbb9713cc30ac692d5f7a5f0ee4f25a4a83\",\"country\":\"US\",\"reachability\":1,\"bundle_id\":\"com.motionvolt.flipdiving\",\"wrapper_version\":\"Unity 5.4.2f1\",\"language\":\"en\",\"is_portrait\":1,\"model\":\"Nexus 6\"}]", 
        "protocol": "HTTPS", 
        "referrer": null, 
        "scr_port": 38748, 
        "src_ip": "-", 
        "tk_flag": null, 
        "ts": "1489436418097", 
        "uri": "/api/config", 
        "user_agent": null
    }, 
    "1489436418254,44486ab2-2d14-4b42-bd82-6c97b04862f2": {
        "domain": "", 
        "dst_ip": "52.1.42.145", 
        "dst_port": 443, 
        "headers": {
            "accept": "application/json", 
            "accept-encoding": "gzip", 
            "connection": "Keep-Alive", 
            "content-length": "857", 
            "content-type": "application/json", 
            "host": "live.chartboost.com", 
            "user-agent": "Dalvik/2.1.0 (Linux; U; Android 7.0; Nexus 6 Build/NBD91Y)", 
            "x-chartboost-api": "6.4.2", 
            "x-chartboost-app": "57ac96abf6cd450a53bd8003", 
            "x-chartboost-client": "Chartboost-Android-SDK Unity 6.4.2", 
            "x-chartboost-signature": "b1449f265685bfc5fa2cc38527743f95d7145554"
        }, 
        "host": "live.chartboost.com", 
        "is_foreground": true, 
        "is_host_ip": 0, 
        "label": 0, 
        "md5": null, 
        "method": "POST", 
        "package_name": "com.motionvolt.flipdiving", 
        "package_version": "2.6.7", 
        "pii_types": null, 
        "platform": "android", 
        "post_body": "[{\"tracking\":0,\"device_type\":\"motorola Nexus 6\",\"sdk\":\"6.4.2\",\"dpi\":\"560\",\"carrier\":{\"phone-type\":1,\"carrier-name\":\"T-Mobile\",\"iso-country-code\":\"us\",\"mobile-country-code\":\"202\",\"mobile-network-code\":\"01\"},\"timestamp\":\"1489436417\",\"identity\":\"eyJ1dWlkIjoiNDZkZjc5MDBhYTYyNzQzZiIsIm1hY2lkIjoiMmY1NjcyY2I3NjY5MWI5ODliYmQy\\nMDIyYTUzNDk5MzlhMmQ3Yjk1MiIsImdhaWQiOiJjN2JhYmY4ODdiODQ0NWM2YjQzNDA1NjE4N2Q4\\nNTg3MyJ9\\n\",\"rooted_device\":false,\"bundle\":\"2.6.7\",\"dh\":\"2392\",\"scale\":\"3.5\",\"dw\":\"1440\",\"session\":1,\"mobile_network\":13,\"framework_version\":\"6.4.5\",\"app\":\"57ac96abf6cd450a53bd8003\",\"h\":\"2392\",\"os\":\"Android 7.0\",\"timezone\":\"GMT-07:00\",\"w\":\"1440\",\"commit_hash\":\"b9500dbb9713cc30ac692d5f7a5f0ee4f25a4a83\",\"country\":\"US\",\"reachability\":1,\"bundle_id\":\"com.motionvolt.flipdiving\",\"wrapper_version\":\"Unity 5.4.2f1\",\"language\":\"en\",\"is_portrait\":1,\"model\":\"Nexus 6\"}]", 
        "protocol": "HTTPS", 
        "referrer": null, 
        "scr_port": 38748, 
        "src_ip": "-", 
        "tk_flag": null, 
        "ts": "1489436418254", 
        "uri": "/api/install", 
        "user_agent": null
    }, 
    "1489436418421,fdf8d048-df0a-4ff0-9578-c28631d4372b": {
        "domain": "", 
        "dst_ip": "52.1.42.145", 
        "dst_port": 443, 
        "headers": {
            "accept": "application/json", 
            "accept-encoding": "gzip", 
            "connection": "Keep-Alive", 
            "content-length": "1081", 
            "content-type": "application/json", 
            "host": "live.chartboost.com", 
            "user-agent": "Dalvik/2.1.0 (Linux; U; Android 7.0; Nexus 6 Build/NBD91Y)", 
            "x-chartboost-api": "6.4.2", 
            "x-chartboost-app": "57ac96abf6cd450a53bd8003", 
            "x-chartboost-client": "Chartboost-Android-SDK Unity 6.4.2", 
            "x-chartboost-signature": "8a3d403b2b63c255dde5f43c45cfaf0f368513a6"
        }, 
        "host": "live.chartboost.com", 
        "is_foreground": true, 
        "is_host_ip": 0, 
        "label": 0, 
        "md5": null, 
        "method": "POST", 
        "package_name": "com.motionvolt.flipdiving", 
        "package_version": "2.6.7", 
        "pii_types": null, 
        "platform": "android", 
        "post_body": "[{\"device\":{\"tracking\":0,\"dw\":\"1440\",\"device_type\":\"motorola Nexus 6\",\"dpi\":\"560\",\"mobile_network\":13,\"carrier\":{\"mobile_network_code\":\"01\",\"carrier_name\":\"T-Mobile\",\"phone_type\":1,\"iso_country_code\":\"us\",\"mobile_country_code\":\"202\"},\"timestamp\":\"1489436417\",\"identity\":\"eyJ1dWlkIjoiNDZkZjc5MDBhYTYyNzQzZiIsIm1hY2lkIjoiMmY1NjcyY2I3NjY5MWI5ODliYmQy\\nMDIyYTUzNDk5MzlhMmQ3Yjk1MiIsImdhaWQiOiJjN2JhYmY4ODdiODQ0NWM2YjQzNDA1NjE4N2Q4\\nNTg3MyJ9\\n\",\"rooted_device\":false,\"h\":\"2392\",\"w\":\"1440\",\"os\":\"Android 7.0\",\"timezone\":\"GMT-07:00\",\"device_family\":\"\",\"country\":\"US\",\"reachability\":1,\"dh\":\"2392\",\"retina\":false,\"language\":\"en\",\"scale\":\"3.5\",\"model\":\"Nexus 6\",\"is_portrait\":1},\"app\":{\"session_id\":\"\",\"ui\":-1,\"bundle\":\"2.6.7\",\"test_mode\":false,\"app\":\"57ac96abf6cd450a53bd8003\",\"bundle_id\":\"com.motionvolt.flipdiving\"},\"ad\":{\"retry_count\":0,\"amount\":0,\"cache_assets\":{\"videos\":[],\"templates\":[]},\"session\":1,\"location\":\"\",\"cache\":false},\"sdk\":{\"sdk\":\"6.4.2\",\"commit_hash\":\"b9500dbb9713cc30ac692d5f7a5f0ee4f25a4a83\",\"wrapper_version\":\"Unity 5.4.2f1\",\"framework\":\"\",\"framework_version\":\"6.4.5\"}}]", 
        "protocol": "HTTPS", 
        "referrer": null, 
        "scr_port": 38764, 
        "src_ip": "-", 
        "tk_flag": null, 
        "ts": "1489436418421", 
        "uri": "/webview/v2/prefetch", 
        "user_agent": null
    }, 
    "1489436419248,90711bd0-7c18-45b8-ab01-57d6ea632dad": {
        "domain": "", 
        "dst_ip": "146.0.239.24", 
        "dst_port": 443, 
        "headers": {
            "accept-encoding": "gzip", 
            "connection": "Keep-Alive", 
            "host": "engine.fyber.com", 
            "user-agent": "Dalvik/2.1.0 (Linux; U; Android 7.0; Nexus 6 Build/NBD91Y)"
        }, 
        "host": "engine.fyber.com", 
        "is_foreground": true, 
        "is_host_ip": 0, 
        "label": 1, 
        "md5": null, 
        "method": "GET", 
        "package_name": "com.motionvolt.flipdiving", 
        "package_version": "2.6.7", 
        "pii_types": [
            "AdvertiserId"
        ], 
        "platform": "android", 
        "post_body": null, 
        "protocol": "HTTPS", 
        "referrer": null, 
        "scr_port": 41664, 
        "src_ip": "-", 
        "tk_flag": null, 
        "ts": "1489436419248", 
        "uri": "/sdk-config?google_ad_id=RECON_AdvertiserId&carrier_country=us&framework_version=5.4.2f1&appid=45975&timestamp=1489436418&google_ad_id_limited_tracking_enabled=false&phone_version=motorola_Nexus 6&carrier_name=T-Mobile&sdk_features=MPI,VPL,JUD,BLE,INV,IVE&plugin_version=8.5.5&platform=android&network_connection_type=wifi&app_version=2.6.7&app_bundle_name=com.motionvolt.flipdiving&client=sdk&sdk_version=8.5.5&uid=030c8b77a31bd5abc0c54421d172316da7e5b2b1&manufacturer=motorola&language=en_US&os_version=7.0&framework=unity&signature=5efe623b5d88eaacdb3d6e593ae49ddf283917f8", 
        "user_agent": null
    }, 
    "1489436421496,2c47451a-9b78-4b32-8e33-44494edce294": {
        "domain": "", 
        "dst_ip": "54.152.238.200", 
        "dst_port": 443, 
        "headers": {
            "accept-encoding": "gzip", 
            "connection": "Keep-Alive", 
            "content-length": "927", 
            "content-type": "application/x-www-form-urlencoded", 
            "host": "androidads23.adcolony.com", 
            "user-agent": "Dalvik/2.1.0 (Linux; U; Android 7.0; Nexus 6 Build/NBD91Y)"
        }, 
        "host": "androidads23.adcolony.com", 
        "is_foreground": true, 
        "is_host_ip": 0, 
        "label": 1, 
        "md5": null, 
        "method": "POST", 
        "package_name": "com.motionvolt.flipdiving", 
        "package_version": "2.6.7", 
        "pii_types": [
            "AdvertiserId"
        ], 
        "platform": "android", 
        "post_body": "{\n  \"os_name\":\"android\",\n  \"os_version\":\"7.0\",\n  \"device_api\":\"24\",\n  \"app_version\":\"1.0\",\n  \"android_id_sha1\":\"\",\n  \"device_id\":\"97bac6cf-ba1e-4c0e-ab44-f25418714a61\",\n  \"open_udid\":\"\",\n  \"device_type\":\"phone\",\n  \"ln\":\"en\",\n  \"device_brand\":\"motorola\",\n  \"device_model\":\"Nexus 6\",\n  \"screen_width\":1440,\n  \"screen_height\":2392,\n  \"sdk_type\":\"android_native\",\n  \"sdk_version\":\"2.3.6\",\n  \"origin_store\":\"google\",\n  \"available_stores\":[\"google\"],\n  \"imei_sha1\":\"\",\n  \"memory_class\":\"256\",\n  \"memory_used_mb\":\"11\",\n  \"advertiser_id\":\"RECON_AdvertiserId\",\n  \"limit_tracking\":false,\n  \"immersion\":true,\n  \"app_id\":\"appd931937344bf4aadaa\",\n  \"zones\":[\"vz40b0bae7d8094cada8\"],\n  \"ad_queue\":\n  {},\n  \"ad_playing\":\n  {},\n  \"ad_history\":\n  {},\n  \"carrier\":\"T-Mobile\",\n  \"network_type\":\"wifi\",\n  \"custom_id\":\"030c8b77a31bd5abc0c54421d172316da7e5b2b1\",\n  \"sid\":\"7a60478a-b37a-450f-82a1-ffde93e7d367\",\n  \"s_imp_count\":0\n}\n", 
        "protocol": "HTTPS", 
        "referrer": null, 
        "scr_port": 41156, 
        "src_ip": "-", 
        "tk_flag": null, 
        "ts": "1489436421496", 
        "uri": "/configure", 
        "user_agent": null
    }, 
    "1489436421574,66501115-c728-4aac-8e05-79f0a78a962d": {
        "domain": "", 
        "dst_ip": "54.83.76.249", 
        "dst_port": 443, 
        "headers": {
            "accept-encoding": "gzip", 
            "connection": "Keep-Alive", 
            "host": "adserver.unityads.unity3d.com", 
            "user-agent": "Dalvik/2.1.0 (Linux; U; Android 7.0; Nexus 6 Build/NBD91Y)"
        }, 
        "host": "adserver.unityads.unity3d.com", 
        "is_foreground": true, 
        "is_host_ip": 0, 
        "label": 0, 
        "md5": null, 
        "method": "GET", 
        "package_name": "com.motionvolt.flipdiving", 
        "package_version": "2.6.7", 
        "pii_types": null, 
        "platform": "android", 
        "post_body": null, 
        "protocol": "HTTPS", 
        "referrer": null, 
        "scr_port": 47439, 
        "src_ip": "-", 
        "tk_flag": null, 
        "ts": "1489436421574", 
        "uri": "/games/1091515/configuration?bundleId=com.motionvolt.flipdiving&encrypted=true&rooted=false", 
        "user_agent": null
    }, 
    "1489436422010,902273c9-b652-4636-a904-df072eeedcf1": {
        "domain": "", 
        "dst_ip": "54.83.76.249", 
        "dst_port": 443, 
        "headers": {
            "accept-encoding": "gzip", 
            "connection": "Keep-Alive", 
            "content-length": "403", 
            "content-type": "application/json", 
            "host": "adserver.unityads.unity3d.com", 
            "user-agent": "Dalvik/2.1.0 (Linux; U; Android 7.0; Nexus 6 Build/NBD91Y)"
        }, 
        "host": "adserver.unityads.unity3d.com", 
        "is_foreground": true, 
        "is_host_ip": 0, 
        "label": 1, 
        "md5": null, 
        "method": "POST", 
        "package_name": "com.motionvolt.flipdiving", 
        "package_version": "2.6.7", 
        "pii_types": [
            "AdvertiserId"
        ], 
        "platform": "android", 
        "post_body": "[{\"mediationName\":\"Fyber\",\"deviceFreeSpace\":46286004,\"networkOperator\":\"310260\",\"webviewUa\":\"Mozilla\\/5.0 (Linux; Android 7.0; Nexus 6 Build\\/NBD91Y; wv) AppleWebKit\\/537.36 (KHTML, like Gecko) Version\\/4.0 Chrome\\/56.0.2924.87 Mobile Safari\\/537.36\",\"networkOperatorName\":\"T-Mobile\",\"language\":\"en_US\",\"bundleId\":\"com.motionvolt.flipdiving\",\"bundleVersion\":\"2.6.7\",\"mediationVersion\":\"8.5.5\",\"timeZone\":\"PST\"}]", 
        "protocol": "HTTPS", 
        "referrer": null, 
        "scr_port": 47439, 
        "src_ip": "-", 
        "tk_flag": null, 
        "ts": "1489436422010", 
        "uri": "/games/1091515/fill?advertisingTrackingId=RECON_AdvertiserId&limitAdTracking=false&deviceMake=motorola&deviceModel=Nexus 6&platform=android&screenDensity=560&screenWidth=1440&screenHeight=2392&sdkVersion=2005&screenSize=268435794&stores=google&apiLevel=24&connectionType=wifi&networkType=13", 
        "user_agent": null
    }, 
    "1489436422901,cb626466-9699-4d48-9dd5-ccc2371eeef2": {
        "domain": "", 
        "dst_ip": "54.175.135.115", 
        "dst_port": 443, 
        "headers": {
            "accept-encoding": "gzip", 
            "connection": "Keep-Alive", 
            "content-length": "176", 
            "content-type": "application/x-www-form-urlencoded", 
            "host": "events3.adcolony.com", 
            "user-agent": "Dalvik/2.1.0 (Linux; U; Android 7.0; Nexus 6 Build/NBD91Y)"
        }, 
        "host": "events3.adcolony.com", 
        "is_foreground": true, 
        "is_host_ip": 0, 
        "label": 0, 
        "md5": null, 
        "method": "POST", 
        "package_name": "com.motionvolt.flipdiving", 
        "package_version": "2.6.7", 
        "pii_types": null, 
        "platform": "android", 
        "post_body": "{\n  \"s_time\":1.2530,\n  \"sid\":\"7a60478a-b37a-450f-82a1-ffde93e7d367\",\n  \"guid\":\"0dcf5221-5641-49f4-98a8-25c673ebaa0f\",\n  \"guid_key\":\"ebe454f9153a872a92d5d7bef14cb66f9935720e\"\n}\n", 
        "protocol": "HTTPS", 
        "referrer": null, 
        "scr_port": 45604, 
        "src_ip": "-", 
        "tk_flag": null, 
        "ts": "1489436422901", 
        "uri": "/t/5.0/install?pl=o_VU9ktRvKwzkCtIda4GHnPNlhZ4X1YfSRCQW9-BlFB4UFjs-1_bYbKyewS3lHNtWQqnKiaxJyzkqKN9erUIo_qKxEQmgsMPqnSFmcuSCdjZSi5OlAeLvtcZ9Ik3Nzn0WbWdkmMOuuhbCfK1enT6SEX6myjXKtyDt3xQDA_IQzBmCW1y0dBY4TpzpcdCfUfiQRPURonUC2pF8amokP3mNIpaxgUlYkb5Bk93tc3gTdh7312BC4mn2Xj2m2q7oKzqZ5UUCrQ9snQoYPI9RQlorZjaCsX2zD491VPz5J9XP99Ili6N3ygg9v5d_fdVUSL1XsCth4KVIUv2S0IS-yABIo2PR1mo5ojMvVqzY-uuCcjwgzwAb2z0obu74siq_bL3hUhWOSrFq5YbsN7UxH0MtXdlKPXOXSIWsF64RzKwgyxF68i3Alf74AfSKMxIePSsmeMmWd601CBttem9tuykuqtoElhdfDDo6IuQqg==", 
        "user_agent": null
    }, 
    "1489436422903,e41b987f-a6c3-446e-8e4d-a2a4aa4c40a7": {
        "domain": "", 
        "dst_ip": "52.204.112.146", 
        "dst_port": 443, 
        "headers": {
            "accept-encoding": "gzip", 
            "connection": "Keep-Alive", 
            "content-length": "176", 
            "content-type": "application/x-www-form-urlencoded", 
            "host": "events3alt.adcolony.com", 
            "user-agent": "Dalvik/2.1.0 (Linux; U; Android 7.0; Nexus 6 Build/NBD91Y)"
        }, 
        "host": "events3alt.adcolony.com", 
        "is_foreground": true, 
        "is_host_ip": 0, 
        "label": 0, 
        "md5": null, 
        "method": "POST", 
        "package_name": "com.motionvolt.flipdiving", 
        "package_version": "2.6.7", 
        "pii_types": null, 
        "platform": "android", 
        "post_body": "{\n  \"s_time\":1.2530,\n  \"sid\":\"7a60478a-b37a-450f-82a1-ffde93e7d367\",\n  \"guid\":\"a0de47d4-e087-4807-9835-ace93bb66bb8\",\n  \"guid_key\":\"108963c293c06aeaac5a738d7c55914ad172ae8a\"\n}\n", 
        "protocol": "HTTPS", 
        "referrer": null, 
        "scr_port": 38389, 
        "src_ip": "-", 
        "tk_flag": null, 
        "ts": "1489436422903", 
        "uri": "/t/5.0/session_start?pl=o_VU9ktRvKwzkCtIda4GHnPNlhZ4X1YfSRCQW9-BlFB4UFjs-1_bYbKyewS3lHNtWQqnKiaxJyzkqKN9erUIo_qKxEQmgsMPqnSFmcuSCdjZSi5OlAeLvtcZ9Ik3Nzn0WbWdkmMOuuhbCfK1enT6SEX6myjXKtyDt3xQDA_IQzBmCW1y0dBY4TpzpcdCfUfiQRPURonUC2pF8amokP3mNIpaxgUlYkb5Bk93tc3gTdh7312BC4mn2Xj2m2q7oKzqZ5UUCrQ9snQoYPI9RQlorZjaCsX2zD491VPz5J9XP99Ili6N3ygg9v5d_fdVUSL1XsCth4KVIUv2S0IS-yABIo2PR1mo5ojMvVqzY-uuCcjwgzwAb2z0obu74siq_bL3hUhWOSrFq5YbsN7UxH0MtXdlKPXOXSIWsF64RzKwgyxF68i3Alf74AfSKMxIePSsmeMmWd601CBttem9tuykuqtoElhdfDDo6IuQqg==", 
        "user_agent": null
    }, 
    "1489436423708,196f58c3-9151-4f3e-b5cd-151b8c5d2dee": {
        "domain": "", 
        "dst_ip": "192.229.211.63", 
        "dst_port": 443, 
        "headers": {
            "accept-encoding": "gzip", 
            "connection": "Keep-Alive", 
            "host": "cdn-lb.vungle.com", 
            "user-agent": "Mozilla/5.0 (Linux; Android 7.0; Nexus 6 Build/NBD91Y; wv) AppleWebKit/537.36 (KHTML, like Gecko) Version/4.0 Chrome/56.0.2924.87 Mobile Safari/537.36"
        }, 
        "host": "cdn-lb.vungle.com", 
        "is_foreground": true, 
        "is_host_ip": 0, 
        "label": 0, 
        "md5": null, 
        "method": "GET", 
        "package_name": "com.motionvolt.flipdiving", 
        "package_version": "2.6.7", 
        "pii_types": null, 
        "platform": "android", 
        "post_body": null, 
        "protocol": "HTTPS", 
        "referrer": null, 
        "scr_port": 41215, 
        "src_ip": "-", 
        "tk_flag": null, 
        "ts": "1489436423708", 
        "uri": "/bundles/589c7a87d484865c490000d3-CUSTOM-1.zip", 
        "user_agent": null
    }, 
    "1489436423752,563c2477-e1f8-4e2a-9b5c-757eea41ba27": {
        "domain": "", 
        "dst_ip": "38.68.168.127", 
        "dst_port": 443, 
        "headers": {
            "accept-encoding": "gzip", 
            "connection": "Keep-Alive", 
            "host": "cdn-lb.vungle.com", 
            "user-agent": "Mozilla/5.0 (Linux; Android 7.0; Nexus 6 Build/NBD91Y; wv) AppleWebKit/537.36 (KHTML, like Gecko) Version/4.0 Chrome/56.0.2924.87 Mobile Safari/537.36"
        }, 
        "host": "cdn-lb.vungle.com", 
        "is_foreground": true, 
        "is_host_ip": 0, 
        "label": 0, 
        "md5": null, 
        "method": "GET", 
        "package_name": "com.motionvolt.flipdiving", 
        "package_version": "2.6.7", 
        "pii_types": null, 
        "platform": "android", 
        "post_body": null, 
        "protocol": "HTTPS", 
        "referrer": null, 
        "scr_port": 42223, 
        "src_ip": "-", 
        "tk_flag": null, 
        "ts": "1489436423752", 
        "uri": "/zen/AB2_ScreenshotVideo001_15s_Feb17_1080x1920_And-720x1280-Q2.mp4", 
        "user_agent": null
    }, 
    "1489436431112,4cc1b9b8-7c8f-46b2-a0df-94d0c86d27d4": {
        "domain": "", 
        "dst_ip": "52.1.42.145", 
        "dst_port": 443, 
        "headers": {
            "accept": "application/json", 
            "accept-encoding": "gzip", 
            "connection": "Keep-Alive", 
            "content-length": "1094", 
            "content-type": "application/json", 
            "host": "live.chartboost.com", 
            "user-agent": "Dalvik/2.1.0 (Linux; U; Android 7.0; Nexus 6 Build/NBD91Y)", 
            "x-chartboost-api": "6.4.2", 
            "x-chartboost-app": "57ac96abf6cd450a53bd8003", 
            "x-chartboost-client": "Chartboost-Android-SDK Unity 6.4.2", 
            "x-chartboost-signature": "46b178d0dfe3ffc06ad4a8288d3bdcc25fa09a60"
        }, 
        "host": "live.chartboost.com", 
        "is_foreground": true, 
        "is_host_ip": 0, 
        "label": 0, 
        "md5": null, 
        "method": "POST", 
        "package_name": "com.motionvolt.flipdiving", 
        "package_version": "2.6.7", 
        "pii_types": null, 
        "platform": "android", 
        "post_body": "[{\"device\":{\"tracking\":0,\"dw\":\"1440\",\"device_type\":\"motorola Nexus 6\",\"dpi\":\"560\",\"mobile_network\":13,\"carrier\":{\"mobile_network_code\":\"01\",\"carrier_name\":\"T-Mobile\",\"phone_type\":1,\"iso_country_code\":\"us\",\"mobile_country_code\":\"202\"},\"timestamp\":\"1489436417\",\"identity\":\"eyJ1dWlkIjoiNDZkZjc5MDBhYTYyNzQzZiIsIm1hY2lkIjoiMmY1NjcyY2I3NjY5MWI5ODliYmQy\\nMDIyYTUzNDk5MzlhMmQ3Yjk1MiIsImdhaWQiOiJjN2JhYmY4ODdiODQ0NWM2YjQzNDA1NjE4N2Q4\\nNTg3MyJ9\\n\",\"rooted_device\":false,\"h\":\"2392\",\"w\":\"1440\",\"os\":\"Android 7.0\",\"timezone\":\"GMT-07:00\",\"device_family\":\"\",\"country\":\"US\",\"reachability\":1,\"dh\":\"2392\",\"retina\":false,\"language\":\"en\",\"scale\":\"3.5\",\"model\":\"Nexus 6\",\"is_portrait\":1},\"app\":{\"session_id\":\"\",\"ui\":-1,\"bundle\":\"2.6.7\",\"test_mode\":false,\"app\":\"57ac96abf6cd450a53bd8003\",\"bundle_id\":\"com.motionvolt.flipdiving\"},\"ad\":{\"retry_count\":0,\"amount\":0,\"session\":1,\"cache_assets\":{\"videos\":[],\"templates\":[]},\"location\":\"CrossPromotion\",\"cache\":true},\"sdk\":{\"sdk\":\"6.4.2\",\"commit_hash\":\"b9500dbb9713cc30ac692d5f7a5f0ee4f25a4a83\",\"wrapper_version\":\"Unity 5.4.2f1\",\"framework\":\"\",\"framework_version\":\"6.4.5\"}}]", 
        "protocol": "HTTPS", 
        "referrer": null, 
        "scr_port": 38817, 
        "src_ip": "-", 
        "tk_flag": null, 
        "ts": "1489436431112", 
        "uri": "/webview/v2/interstitial/get", 
        "user_agent": null
    }
}