{
    "1489435969276,8e45cf0c-01b5-4160-998b-8e83bf57e143": {
        "domain": "", 
        "dst_ip": "198.232.124.36", 
        "dst_port": 443, 
        "headers": {
            "accept-encoding": "gzip", 
            "connection": "Keep-Alive", 
            "host": "ua.supersonicads.com", 
            "user-agent": "Dalvik/2.1.0 (Linux; U; Android 7.0; Nexus 6 Build/NBD91Y)"
        }, 
        "host": "ua.supersonicads.com", 
        "is_foreground": true, 
        "is_host_ip": 0, 
        "label": 1, 
        "md5": null, 
        "method": "GET", 
        "package_name": "com.yodo1.crossyroad", 
        "package_version": "2.3.1", 
        "pii_types": [
            "AdvertiserId"
        ], 
        "platform": "android", 
        "post_body": null, 
        "protocol": "HTTPS", 
        "referrer": null, 
        "scr_port": 48208, 
        "src_ip": "-", 
        "tk_flag": null, 
        "ts": "1489435969276", 
        "uri": "/api/rest/v1.1/uniqueusers?applicationKey=3ec5fbe1&applicationUserId=RECON_AdvertiserId&sdkVersion=6.4.17", 
        "user_agent": null
    }, 
    "1489435969806,1374a59c-b335-4a55-bbc6-f36327bdcf59": {
        "domain": "", 
        "dst_ip": "176.34.137.133", 
        "dst_port": 443, 
        "headers": {
            "accept-encoding": "gzip", 
            "connection": "Keep-Alive", 
            "host": "init.supersonicads.com", 
            "user-agent": "Dalvik/2.1.0 (Linux; U; Android 7.0; Nexus 6 Build/NBD91Y)"
        }, 
        "host": "init.supersonicads.com", 
        "is_foreground": true, 
        "is_host_ip": 0, 
        "label": 1, 
        "md5": null, 
        "method": "GET", 
        "package_name": "com.yodo1.crossyroad", 
        "package_version": "2.3.1", 
        "pii_types": [
            "AdvertiserId", 
            "AdvertiserId"
        ], 
        "platform": "android", 
        "post_body": null, 
        "protocol": "HTTPS", 
        "referrer": null, 
        "scr_port": 49586, 
        "src_ip": "-", 
        "tk_flag": null, 
        "ts": "1489435969806", 
        "uri": "/sdk/v6.4.17?platform=android&applicationKey=3ec5fbe1&applicationUserId=RECON_AdvertiserId&sdkVersion=6.4.17&advId=RECON_AdvertiserId", 
        "user_agent": null
    }, 
    "1489435970011,74c84a99-cc96-4cc6-b2ff-f92e46949873": {
        "domain": "", 
        "dst_ip": "34.248.182.34", 
        "dst_port": 443, 
        "headers": {
            "accept-encoding": "gzip", 
            "connection": "Keep-Alive", 
            "host": "www.supersonicads.com", 
            "user-agent": "Dalvik/2.1.0 (Linux; U; Android 7.0; Nexus 6 Build/NBD91Y)"
        }, 
        "host": "www.supersonicads.com", 
        "is_foreground": true, 
        "is_host_ip": 0, 
        "label": 0, 
        "md5": null, 
        "method": "GET", 
        "package_name": "com.yodo1.crossyroad", 
        "package_version": "2.3.1", 
        "pii_types": null, 
        "platform": "android", 
        "post_body": null, 
        "protocol": "HTTPS", 
        "referrer": null, 
        "scr_port": 49323, 
        "src_ip": "-", 
        "tk_flag": null, 
        "ts": "1489435970011", 
        "uri": "/timestamp.php", 
        "user_agent": null
    }, 
    "1489435970023,dfae0e01-fea4-402e-905e-098676b3e1a5": {
        "domain": "", 
        "dst_ip": "146.0.239.45", 
        "dst_port": 443, 
        "headers": {
            "accept-encoding": "gzip", 
            "connection": "Keep-Alive", 
            "host": "engine.fyber.com", 
            "user-agent": "Dalvik/2.1.0 (Linux; U; Android 7.0; Nexus 6 Build/NBD91Y)"
        }, 
        "host": "engine.fyber.com", 
        "is_foreground": true, 
        "is_host_ip": 0, 
        "label": 1, 
        "md5": null, 
        "method": "GET", 
        "package_name": "com.yodo1.crossyroad", 
        "package_version": "2.3.1", 
        "pii_types": [
            "AdvertiserId"
        ], 
        "platform": "android", 
        "post_body": null, 
        "protocol": "HTTPS", 
        "referrer": null, 
        "scr_port": 48523, 
        "src_ip": "-", 
        "tk_flag": null, 
        "ts": "1489435970023", 
        "uri": "/video-cache?google_ad_id=RECON_AdvertiserId&carrier_country=us&appid=26553&google_ad_id_limited_tracking_enabled=false&phone_version=motorola_Nexus 6&sdk_features=MPI,VPL,JUD,BLE,INV,IVE&carrier_name=T-Mobile&platform=android&network_connection_type=wifi&app_version=2.3.1&app_bundle_name=com.yodo1.crossyroad&sdk_version=8.6.0&client=sdk&uid=1b8034dd0cf700b55d8738c86fff8c9029c34cab&language=en_US&os_version=7.0&manufacturer=motorola", 
        "user_agent": null
    }, 
    "1489435970254,9084a529-1fa7-4c14-9ee3-5f9a65d1ed6d": {
        "domain": "", 
        "dst_ip": "34.248.182.34", 
        "dst_port": 443, 
        "headers": {
            "accept-encoding": "gzip", 
            "connection": "Keep-Alive", 
            "host": "www.supersonicads.com", 
            "user-agent": "Dalvik/2.1.0 (Linux; U; Android 7.0; Nexus 6 Build/NBD91Y)"
        }, 
        "host": "www.supersonicads.com", 
        "is_foreground": true, 
        "is_host_ip": 0, 
        "label": 1, 
        "md5": null, 
        "method": "GET", 
        "package_name": "com.yodo1.crossyroad", 
        "package_version": "2.3.1", 
        "pii_types": [
            "AdvertiserId"
        ], 
        "platform": "android", 
        "post_body": null, 
        "protocol": "HTTPS", 
        "referrer": null, 
        "scr_port": 49323, 
        "src_ip": "-", 
        "tk_flag": null, 
        "ts": "1489435970254", 
        "uri": "/campaigns/onLoad?&bundleId=com.yodo1.crossyroad&deviceIds[AID]=RECON_AdvertiserId&isLimitAdTrackingEnabled=false&signature=eb5f184e2c89d90c20bc3d0b375cd633", 
        "user_agent": null
    }, 
    "1489435970983,d82f3211-cb15-4385-bbf7-56dfe797a7fd": {
        "domain": "", 
        "dst_ip": "140.205.34.5", 
        "dst_port": 443, 
        "headers": {
            "connection": "Keep-Alive", 
            "host": "uop.umeng.com"
        }, 
        "host": "uop.umeng.com", 
        "is_foreground": true, 
        "is_host_ip": 0, 
        "label": 0, 
        "md5": null, 
        "method": "GET", 
        "package_name": "com.yodo1.crossyroad", 
        "package_version": "2.3.1", 
        "pii_types": null, 
        "platform": "android", 
        "post_body": null, 
        "protocol": "HTTPS", 
        "referrer": null, 
        "scr_port": 37493, 
        "src_ip": "-", 
        "tk_flag": null, 
        "ts": "1489435970983", 
        "uri": "/", 
        "user_agent": null
    }, 
    "1489435971276,0a9409be-9e4a-475b-8126-203dedee7a17": {
        "domain": "", 
        "dst_ip": "107.21.244.54", 
        "dst_port": 443, 
        "headers": {
            "accept-encoding": "gzip", 
            "connection": "close", 
            "content-length": "1403", 
            "content-type": "application/x-www-form-urlencoded", 
            "host": "connect.tapjoy.com", 
            "user-agent": "Dalvik/2.1.0 (Linux; U; Android 7.0; Nexus 6 Build/NBD91Y)"
        }, 
        "host": "connect.tapjoy.com", 
        "is_foreground": true, 
        "is_host_ip": 0, 
        "label": 1, 
        "md5": null, 
        "method": "POST", 
        "package_name": "com.yodo1.crossyroad", 
        "package_version": "2.3.1", 
        "pii_types": [
            "AndroidId", 
            "AdvertiserId", 
            "AndroidId"
        ], 
        "platform": "android", 
        "post_body": "device_type=android&friend_count=0&display_h=1440&device_manufacturer=motorola&install_id=0c7245bf85d56394f50599f9342dd8bb750f1cdca47a3516ed7354c744741c29&pkg_sign=Pzqln2Fz5In6UD2u%2B4Syj%2F3yqhM%3D&pkg_ver=2.3.1&sdk_type=event&store_view=true&carrier_name=T-Mobile&user_level=0&purchase_total_count=0&display_d=560&connection_type=wifi&installed=1489432871167&mobile_network_code=260&pkg_id=com.yodo1.crossyroad&android_id=RECON_AndroidId&library_version=11.7.0&advertising_id=RECON_AdvertiserId&verifier=f96c0561c9a7ed4da85cdc0bebd363331695e2946b9afb080506032e774e75dc&analytics_id=RECON_AndroidId&screen_layout_size=2&device_location=false&purchase_last_at=0&plugin=native&library_revision=99b668c&timezone=America%2FLos_Angeles&platform=android&session_last_length=0&country_sim=GR&bridge_version=1.0.7&display_w=2392&purchase_last_price=0.0&session_total_count=1&language_code=en&country_code=US&display_multiplier=1.0&timestamp=1489435970&session_last_at=0&carrier_country_code=us&session_total_length=0&session_id=b0859b6c8f2c277f4a736ab2d07ebb709be8325184e5a5d4a3b7f5d582bdb85a&fq7=1&app_id=f4930608-e501-42ca-acd5-53fd4f5a5a4c&mac_address=020000000000&device_gps_version=10298430&screen_density=560&pkg_rev=95&mobile_country_code=310&app_version=2.3.1&purchase_total_price=0.0&device_name=Nexus%206&os_version=7.0&packaged_gps_version=9877000&ad_tracking_enabled=true&fq30=1", 
        "protocol": "HTTPS", 
        "referrer": null, 
        "scr_port": 44332, 
        "src_ip": "-", 
        "tk_flag": null, 
        "ts": "1489435971276", 
        "uri": "/api/connect/v3.json", 
        "user_agent": null
    }, 
    "1489435972475,f7117133-8808-4712-adaa-d7e72ae27dce": {
        "domain": "", 
        "dst_ip": "54.243.229.110", 
        "dst_port": 443, 
        "headers": {
            "accept": "text/html,application/xhtml+xml,application/xml;q=0.9,image/webp,*/*;q=0.8", 
            "accept-encoding": "gzip, deflate", 
            "accept-language": "en-US", 
            "connection": "keep-alive", 
            "host": "ws.tapjoyads.com", 
            "upgrade-insecure-requests": "1", 
            "user-agent": "Mozilla/5.0 (Linux; Android 7.0; Nexus 6 Build/NBD91Y; wv) AppleWebKit/537.36 (KHTML, like Gecko) Version/4.0 Chrome/56.0.2924.87 Mobile Safari/537.36", 
            "x-requested-with": "com.yodo1.crossyroad"
        }, 
        "host": "ws.tapjoyads.com", 
        "is_foreground": true, 
        "is_host_ip": 0, 
        "label": 1, 
        "md5": null, 
        "method": "GET", 
        "package_name": "com.yodo1.crossyroad", 
        "package_version": "2.3.1", 
        "pii_types": [
            "AndroidId", 
            "AdvertiserId", 
            "AndroidId"
        ], 
        "platform": "android", 
        "post_body": null, 
        "protocol": "HTTPS", 
        "referrer": null, 
        "scr_port": 42781, 
        "src_ip": "-", 
        "tk_flag": null, 
        "ts": "1489435972475", 
        "uri": "/events/proxy?device_type=android&friend_count=0&display_h=1440&device_manufacturer=motorola&install_id=0c7245bf85d56394f50599f9342dd8bb750f1cdca47a3516ed7354c744741c29&pkg_sign=Pzqln2Fz5In6UD2u%2B4Syj%2F3yqhM%3D&pkg_ver=2.3.1&sdk_type=event&managed_device_id=tjid.5fb9a0244c174270ac8faad7a5a86f96&store_view=true&carrier_name=T-Mobile&user_level=0&purchase_total_count=0&display_d=560&connection_type=wifi&installed=1489432871167&mobile_network_code=260&pkg_id=com.yodo1.crossyroad&android_id=RECON_AndroidId&library_version=11.7.0&advertising_id=RECON_AdvertiserId&analytics_id=RECON_AndroidId&screen_layout_size=2&device_location=false&purchase_last_at=0&plugin=native&library_revision=99b668c&store=android.GooglePlay&timezone=America%2FLos_Angeles&platform=android&session_last_length=0&app_group_id=584f6429-745d-8000-8000-724699000518&country_sim=GR&analytics_api_key=WE9kKXRdgACAAHJGmQAFGAExCrazt0M1SIR31Rhdly1aMZCFLaikUA4x9BjD&bridge_version=1.0.7&display_w=2392&purchase_last_price=0.0&session_total_count=1&language_code=en&country_code=US&display_multiplier=1.0&session_last_at=0&carrier_country_code=us&session_total_length=0&session_id=b0859b6c8f2c277f4a736ab2d07ebb709be8325184e5a5d4a3b7f5d582bdb85a&fq7=1&app_id=f4930608-e501-42ca-acd5-53fd4f5a5a4c&mac_address=020000000000&device_gps_version=10298430&screen_density=560&pkg_rev=95&mobile_country_code=310&app_version=2.3.1&purchase_total_price=0.0&device_name=Nexus%206&os_version=7.0&packaged_gps_version=9877000&ad_tracking_enabled=true&fq30=1", 
        "user_agent": null
    }, 
    "1489435972493,7408c29c-07ee-481a-ab90-335b2c5d9e35": {
        "domain": "", 
        "dst_ip": "192.225.158.154", 
        "dst_port": 443, 
        "headers": {
            "accept-langauge": "en-US", 
            "connection": "Keep-Alive", 
            "host": "content-js.tapjoy.com", 
            "user-agent": "Mozilla/5.0 (Linux; Android 7.0; Nexus 6 Build/NBD91Y; wv) AppleWebKit/537.36 (KHTML, like Gecko) Version/4.0 Chrome/56.0.2924.87 Mobile Safari/537.36"
        }, 
        "host": "content-js.tapjoy.com", 
        "is_foreground": true, 
        "is_host_ip": 0, 
        "label": 0, 
        "md5": null, 
        "method": "GET", 
        "package_name": "com.yodo1.crossyroad", 
        "package_version": "2.3.1", 
        "pii_types": null, 
        "platform": "android", 
        "post_body": null, 
        "protocol": "HTTPS", 
        "referrer": null, 
        "scr_port": 41597, 
        "src_ip": "-", 
        "tk_flag": null, 
        "ts": "1489435972493", 
        "uri": "/fp/mobile/conf?osVersion=7.0&session_id=c342c5a4eb0b41aab2b81363b789178a&org_id=rrx68giz&sdk_version=3.2-100&os=android", 
        "user_agent": null
    }, 
    "1489435972552,ebd80fc5-c215-4b9c-9c7f-da4dfd0ef93c": {
        "domain": "", 
        "dst_ip": "52.86.96.94", 
        "dst_port": 443, 
        "headers": {
            "accept-encoding": "gzip", 
            "connection": "close", 
            "content-length": "1741", 
            "content-type": "application/x-www-form-urlencoded", 
            "host": "placements.tapjoy.com", 
            "user-agent": "Dalvik/2.1.0 (Linux; U; Android 7.0; Nexus 6 Build/NBD91Y)"
        }, 
        "host": "placements.tapjoy.com", 
        "is_foreground": true, 
        "is_host_ip": 0, 
        "label": 1, 
        "md5": null, 
        "method": "POST", 
        "package_name": "com.yodo1.crossyroad", 
        "package_version": "2.3.1", 
        "pii_types": [
            "AndroidId", 
            "AdvertiserId", 
            "AndroidId", 
            "AdvertiserId"
        ], 
        "platform": "android", 
        "post_body": "device_type=android&friend_count=0&display_h=1440&device_manufacturer=motorola&install_id=0c7245bf85d56394f50599f9342dd8bb750f1cdca47a3516ed7354c744741c29&pkg_sign=Pzqln2Fz5In6UD2u%2B4Syj%2F3yqhM%3D&pkg_ver=2.3.1&sdk_type=event&managed_device_id=tjid.5fb9a0244c174270ac8faad7a5a86f96&store_view=true&carrier_name=T-Mobile&user_level=0&purchase_total_count=0&event_preload=true&display_d=560&connection_type=wifi&installed=1489432871167&mobile_network_code=260&pkg_id=com.yodo1.crossyroad&debug=true&android_id=RECON_AndroidId&library_version=11.7.0&advertising_id=RECON_AdvertiserId&verifier=91c8c4d768120b4a362a720ae430bbc84ce3163ee4eff5bb568be1a7fbfe18f5&analytics_id=RECON_AndroidId&screen_layout_size=2&device_location=false&purchase_last_at=0&plugin=native&library_revision=99b668c&store=android.GooglePlay&timezone=America%2FLos_Angeles&platform=android&session_last_length=0&app_group_id=584f6429-745d-8000-8000-724699000518&country_sim=GR&analytics_api_key=WE9kKXRdgACAAHJGmQAFGAExCrazt0M1SIR31Rhdly1aMZCFLaikUA4x9BjD&bridge_version=1.0.7&display_w=2392&purchase_last_price=0.0&session_total_count=1&language_code=en&country_code=US&display_multiplier=1.0&timestamp=1489435971&session_last_at=0&publisher_user_id=RECON_AdvertiserId&carrier_country_code=us&session_total_length=0&event_name=AppLaunch&session_id=b0859b6c8f2c277f4a736ab2d07ebb709be8325184e5a5d4a3b7f5d582bdb85a&fq7=1&app_id=f4930608-e501-42ca-acd5-53fd4f5a5a4c&mac_address=020000000000&device_gps_version=10298430&screen_density=560&pkg_rev=95&mobile_country_code=310&app_version=2.3.1&purchase_total_price=0.0&device_name=Nexus%206&os_version=7.0&packaged_gps_version=9877000&system_placement=true&ad_tracking_enabled=true&fq30=1", 
        "protocol": "HTTPS", 
        "referrer": null, 
        "scr_port": 40785, 
        "src_ip": "-", 
        "tk_flag": null, 
        "ts": "1489435972552", 
        "uri": "/v1/apps/f4930608-e501-42ca-acd5-53fd4f5a5a4c/content", 
        "user_agent": null
    }, 
    "1489435972761,a1ff6454-98f7-4e9b-8ed3-c3d1932a230f": {
        "domain": "", 
        "dst_ip": "54.243.229.110", 
        "dst_port": 443, 
        "headers": {
            "accept-encoding": "gzip", 
            "connection": "Keep-Alive", 
            "host": "ws.tapjoyads.com", 
            "user-agent": "Dalvik/2.1.0 (Linux; U; Android 7.0; Nexus 6 Build/NBD91Y)"
        }, 
        "host": "ws.tapjoyads.com", 
        "is_foreground": true, 
        "is_host_ip": 0, 
        "label": 1, 
        "md5": null, 
        "method": "GET", 
        "package_name": "com.yodo1.crossyroad", 
        "package_version": "2.3.1", 
        "pii_types": [
            "AndroidId", 
            "AdvertiserId", 
            "AndroidId", 
            "AdvertiserId"
        ], 
        "platform": "android", 
        "post_body": null, 
        "protocol": "HTTPS", 
        "referrer": null, 
        "scr_port": 42782, 
        "src_ip": "-", 
        "tk_flag": null, 
        "ts": "1489435972761", 
        "uri": "/set_publisher_user_id?device_type=android&friend_count=0&display_h=1440&device_manufacturer=motorola&install_id=0c7245bf85d56394f50599f9342dd8bb750f1cdca47a3516ed7354c744741c29&pkg_sign=Pzqln2Fz5In6UD2u+4Syj/3yqhM=&pkg_ver=2.3.1&sdk_type=event&managed_device_id=tjid.5fb9a0244c174270ac8faad7a5a86f96&store_view=true&carrier_name=T-Mobile&user_level=0&purchase_total_count=0&display_d=560&connection_type=wifi&installed=1489432871167&mobile_network_code=260&pkg_id=com.yodo1.crossyroad&android_id=RECON_AndroidId&library_version=11.7.0&advertising_id=RECON_AdvertiserId&verifier=91c8c4d768120b4a362a720ae430bbc84ce3163ee4eff5bb568be1a7fbfe18f5&analytics_id=RECON_AndroidId&screen_layout_size=2&device_location=false&purchase_last_at=0&plugin=native&library_revision=99b668c&store=android.GooglePlay&timezone=America/Los_Angeles&platform=android&session_last_length=0&app_group_id=584f6429-745d-8000-8000-724699000518&country_sim=GR&analytics_api_key=WE9kKXRdgACAAHJGmQAFGAExCrazt0M1SIR31Rhdly1aMZCFLaikUA4x9BjD&bridge_version=1.0.7&display_w=2392&purchase_last_price=0.0&session_total_count=1&language_code=en&country_code=US&display_multiplier=1.0&timestamp=1489435971&session_last_at=0&publisher_user_id=RECON_AdvertiserId&carrier_country_code=us&session_total_length=0&session_id=b0859b6c8f2c277f4a736ab2d07ebb709be8325184e5a5d4a3b7f5d582bdb85a&fq7=1&app_id=f4930608-e501-42ca-acd5-53fd4f5a5a4c&mac_address=020000000000&device_gps_version=10298430&screen_density=560&pkg_rev=95&mobile_country_code=310&app_version=2.3.1&purchase_total_price=0.0&device_name=Nexus 6&os_version=7.0&packaged_gps_version=9877000&ad_tracking_enabled=true&fq30=1", 
        "user_agent": null
    }, 
    "1489435972843,c6d3751d-26ab-489f-9aef-4fa91b03aa7f": {
        "domain": "", 
        "dst_ip": "52.86.96.94", 
        "dst_port": 443, 
        "headers": {
            "accept-encoding": "gzip", 
            "connection": "close", 
            "content-length": "1834", 
            "content-type": "application/x-www-form-urlencoded", 
            "host": "placements.tapjoy.com", 
            "user-agent": "Dalvik/2.1.0 (Linux; U; Android 7.0; Nexus 6 Build/NBD91Y)"
        }, 
        "host": "placements.tapjoy.com", 
        "is_foreground": true, 
        "is_host_ip": 0, 
        "label": 1, 
        "md5": null, 
        "method": "POST", 
        "package_name": "com.yodo1.crossyroad", 
        "package_version": "2.3.1", 
        "pii_types": [
            "AndroidId", 
            "AdvertiserId", 
            "AndroidId", 
            "AdvertiserId"
        ], 
        "platform": "android", 
        "post_body": "device_type=android&friend_count=0&display_h=1440&device_manufacturer=motorola&install_id=0c7245bf85d56394f50599f9342dd8bb750f1cdca47a3516ed7354c744741c29&pkg_sign=Pzqln2Fz5In6UD2u%2B4Syj%2F3yqhM%3D&pkg_ver=2.3.1&sdk_type=event&managed_device_id=tjid.5fb9a0244c174270ac8faad7a5a86f96&store_view=true&carrier_name=T-Mobile&user_level=0&purchase_total_count=0&event_preload=true&display_d=560&connection_type=wifi&mediation_agent=supersonic&installed=1489432871167&mediation_id=null&mobile_network_code=260&pkg_id=com.yodo1.crossyroad&debug=true&android_id=RECON_AndroidId&library_version=11.7.0&advertising_id=RECON_AdvertiserId&verifier=91c8c4d768120b4a362a720ae430bbc84ce3163ee4eff5bb568be1a7fbfe18f5&analytics_id=RECON_AndroidId&screen_layout_size=2&device_location=false&purchase_last_at=0&mediation_source=supersonic&plugin=native&library_revision=99b668c&store=android.GooglePlay&timezone=America%2FLos_Angeles&platform=android&session_last_length=0&app_group_id=584f6429-745d-8000-8000-724699000518&country_sim=GR&analytics_api_key=WE9kKXRdgACAAHJGmQAFGAExCrazt0M1SIR31Rhdly1aMZCFLaikUA4x9BjD&bridge_version=1.0.7&display_w=2392&purchase_last_price=0.0&session_total_count=1&language_code=en&country_code=US&display_multiplier=1.0&timestamp=1489435971&session_last_at=0&publisher_user_id=RECON_AdvertiserId&carrier_country_code=us&session_total_length=0&event_name=Failed&session_id=b0859b6c8f2c277f4a736ab2d07ebb709be8325184e5a5d4a3b7f5d582bdb85a&fq7=1&app_id=f4930608-e501-42ca-acd5-53fd4f5a5a4c&mac_address=020000000000&device_gps_version=10298430&screen_density=560&pkg_rev=95&mobile_country_code=310&app_version=2.3.1&purchase_total_price=0.0&device_name=Nexus%206&adapter_version=2.1.1&os_version=7.0&packaged_gps_version=9877000&system_placement=false&ad_tracking_enabled=true&fq30=1", 
        "protocol": "HTTPS", 
        "referrer": null, 
        "scr_port": 40784, 
        "src_ip": "-", 
        "tk_flag": null, 
        "ts": "1489435972843", 
        "uri": "/v1/apps/f4930608-e501-42ca-acd5-53fd4f5a5a4c/mediation_content", 
        "user_agent": null
    }, 
    "1489435973405,48021168-acf3-4366-b73c-e4914ab3704e": {
        "domain": "", 
        "dst_ip": "192.225.158.154", 
        "dst_port": 443, 
        "headers": {
            "accept-encoding": "gzip, deflate", 
            "accept-language": "en-US", 
            "connection": "Keep-Alive", 
            "content-encoding": "gzip", 
            "content-length": "825", 
            "content-type": "application/x-www-form-urlencoded", 
            "cookie": "thx_guid=RECON_AndroidId6c9fb0a42e04a0f7", 
            "host": "content-js.tapjoy.com", 
            "referer": "http://com.yodo1.crossyroad", 
            "user-agent": "Mozilla/5.0 (Linux; Android 7.0; Nexus 6 Build/NBD91Y; wv) AppleWebKit/537.36 (KHTML, like Gecko) Version/4.0 Chrome/56.0.2924.87 Mobile Safari/537.36"
        }, 
        "host": "content-js.tapjoy.com", 
        "is_foreground": true, 
        "is_host_ip": 0, 
        "label": 1, 
        "md5": null, 
        "method": "POST", 
        "package_name": "com.yodo1.crossyroad", 
        "package_version": "2.3.1", 
        "pii_types": [
            "AndroidId"
        ], 
        "platform": "android", 
        "post_body": null, 
        "protocol": "HTTPS", 
        "referrer": null, 
        "scr_port": 41597, 
        "src_ip": "-", 
        "tk_flag": null, 
        "ts": "1489435973405", 
        "uri": "/fp/clear.png", 
        "user_agent": null
    }, 
    "1489435973830,c10dcf76-5c2a-4aaa-97b6-de52b0d3cb42": {
        "domain": "", 
        "dst_ip": "54.243.229.110", 
        "dst_port": 443, 
        "headers": {
            "accept": "image/webp,image/*,*/*;q=0.8", 
            "accept-encoding": "gzip, deflate", 
            "accept-language": "en-US", 
            "connection": "keep-alive", 
            "host": "ws.tapjoyads.com", 
            "referer": "https://ws.tapjoyads.com/events/proxy?device_type=android&friend_count=0&display_h=1440&device_manufacturer=motorola&install_id=0c7245bf85d56394f50599f9342dd8bb750f1cdca47a3516ed7354c744741c29&pkg_sign=Pzqln2Fz5In6UD2u%252B4Syj%252F3yqhM%253D&pkg_ver=2.3.1&sdk_type=event&managed_device_id=tjid.5fb9a0244c174270ac8faad7a5a86f96&store_view=true&carrier_name=T-Mobile&user_level=0&purchase_total_count=0&display_d=560&connection_type=wifi&installed=1489432871167&mobile_network_code=260&pkg_id=com.yodo1.crossyroad&android_id=RECON_AndroidId&library_version=11.7.0&advertising_id=RECON_AdvertiserId&analytics_id=RECON_AndroidId&screen_layout_size=2&device_location=false&purchase_last_at=0&plugin=native&library_revision=99b668c&store=android.GooglePlay&timezone=America%252FLos_Angeles&platform=android&session_last_length=0&app_group_id=584f6429-745d-8000-8000-724699000518&country_sim=GR&analytics_api_key=WE9kKXRdgACAAHJGmQAFGAExCrazt0M1SIR31Rhdly1aMZCFLaikUA4x9BjD&bridge_version=1.0.7&display_w=2392&purchase_last_price=0.0&session_total_count=1&language_code=en&country_code=US&display_multiplier=1.0&session_last_at=0&carrier_country_code=us&session_total_length=0&session_id=b0859b6c8f2c277f4a736ab2d07ebb709be8325184e5a5d4a3b7f5d582bdb85a&fq7=1&app_id=f4930608-e501-42ca-acd5-53fd4f5a5a4c&mac_address=020000000000&device_gps_version=10298430&screen_density=560&pkg_rev=95&mobile_country_code=310&app_version=2.3.1&purchase_total_price=0.0&device_name=Nexus%25206&os_version=7.0&packaged_gps_version=9877000&ad_tracking_enabled=true&fq30=1", 
            "user-agent": "Mozilla/5.0 (Linux; Android 7.0; Nexus 6 Build/NBD91Y; wv) AppleWebKit/537.36 (KHTML, like Gecko) Version/4.0 Chrome/56.0.2924.87 Mobile Safari/537.36", 
            "x-requested-with": "com.yodo1.crossyroad"
        }, 
        "host": "ws.tapjoyads.com", 
        "is_foreground": true, 
        "is_host_ip": 0, 
        "label": 1, 
        "md5": null, 
        "method": "GET", 
        "package_name": "com.yodo1.crossyroad", 
        "package_version": "2.3.1", 
        "pii_types": [
            "AndroidId", 
            "AdvertiserId", 
            "AndroidId"
        ], 
        "platform": "android", 
        "post_body": null, 
        "protocol": "HTTPS", 
        "referrer": null, 
        "scr_port": 42781, 
        "src_ip": "-", 
        "tk_flag": null, 
        "ts": "1489435973830", 
        "uri": "/favicon.ico", 
        "user_agent": null
    }, 
    "1489435985766,e699e590-142f-4b4c-b6a5-757630b54396": {
        "domain": "", 
        "dst_ip": "52.4.122.203", 
        "dst_port": 443, 
        "headers": {
            "accept-encoding": "gzip", 
            "connection": "Keep-Alive", 
            "content-length": "926", 
            "content-type": "application/x-www-form-urlencoded", 
            "host": "outcome.supersonicads.com", 
            "user-agent": "Dalvik/2.1.0 (Linux; U; Android 7.0; Nexus 6 Build/NBD91Y)"
        }, 
        "host": "outcome.supersonicads.com", 
        "is_foreground": true, 
        "is_host_ip": 0, 
        "label": 1, 
        "md5": null, 
        "method": "POST", 
        "package_name": "com.yodo1.crossyroad", 
        "package_version": "2.3.1", 
        "pii_types": [
            "AdvertiserId", 
            "AdvertiserId"
        ], 
        "platform": "android", 
        "post_body": "{\"table\":\"super.dwh.mediation_events\",\"data\":\"{\\\"userId\\\":\\\"RECON_AdvertiserId\\\",\\\"appKey\\\":\\\"3ec5fbe1\\\",\\\"connectionType\\\":\\\"wifi\\\",\\\"isLimitAdTrackingEnabled\\\":\\\"false\\\",\\\"sessionId\\\":\\\"3f3ad05906da4cd09def29f6a99fda361489435969198\\\",\\\"bundleId\\\":\\\"com.yodo1.crossyroad\\\",\\\"mobileCarrier\\\":\\\"T-Mobile\\\",\\\"jb\\\":\\\"false\\\",\\\"timeZone\\\":\\\"GMT-07:00\\\",\\\"internalFreeMemory\\\":45331,\\\"appVersion\\\":\\\"2.3.1\\\",\\\"sdkVersion\\\":\\\"6.4.17\\\",\\\"deviceOEM\\\":\\\"motorola\\\",\\\"osVersion\\\":\\\"24(7.0)\\\",\\\"deviceModel\\\":\\\"Nexus 6\\\",\\\"advertisingId\\\":\\\"RECON_AdvertiserId\\\",\\\"language\\\":\\\"en\\\",\\\"deviceOS\\\":\\\"Android\\\",\\\"externalFreeMemory\\\":45331,\\\"battery\\\":58,\\\"timestamp\\\":1489435970078,\\\"adUnit\\\":2,\\\"InterstitialEvents\\\":[{\\\"provider\\\":\\\"Mediation\\\",\\\"sessionDepth\\\":1,\\\"eventId\\\":21,\\\"timestamp\\\":1489435970070},{\\\"provider\\\":\\\"Mediation\\\",\\\"sessionDepth\\\":1,\\\"eventId\\\":14,\\\"timestamp\\\":1489435968985}]}\"}", 
        "protocol": "HTTPS", 
        "referrer": null, 
        "scr_port": 47939, 
        "src_ip": "-", 
        "tk_flag": null, 
        "ts": "1489435985766", 
        "uri": "/mediation/", 
        "user_agent": null
    }, 
    "1489435986002,acc35744-ed2b-4236-9f0b-823df5522ee6": {
        "domain": "", 
        "dst_ip": "52.4.122.203", 
        "dst_port": 443, 
        "headers": {
            "accept-encoding": "gzip", 
            "connection": "Keep-Alive", 
            "content-length": "921", 
            "content-type": "application/x-www-form-urlencoded", 
            "host": "outcome.supersonicads.com", 
            "user-agent": "Dalvik/2.1.0 (Linux; U; Android 7.0; Nexus 6 Build/NBD91Y)"
        }, 
        "host": "outcome.supersonicads.com", 
        "is_foreground": true, 
        "is_host_ip": 0, 
        "label": 1, 
        "md5": null, 
        "method": "POST", 
        "package_name": "com.yodo1.crossyroad", 
        "package_version": "2.3.1", 
        "pii_types": [
            "AdvertiserId", 
            "AdvertiserId"
        ], 
        "platform": "android", 
        "post_body": "{\"userId\":\"RECON_AdvertiserId\",\"appKey\":\"3ec5fbe1\",\"connectionType\":\"wifi\",\"isLimitAdTrackingEnabled\":\"false\",\"sessionId\":\"3f3ad05906da4cd09def29f6a99fda361489435969198\",\"bundleId\":\"com.yodo1.crossyroad\",\"mobileCarrier\":\"T-Mobile\",\"jb\":\"false\",\"timeZone\":\"GMT-07:00\",\"internalFreeMemory\":45331,\"appVersion\":\"2.3.1\",\"sdkVersion\":\"6.4.17\",\"deviceOEM\":\"motorola\",\"osVersion\":\"24(7.0)\",\"deviceModel\":\"Nexus 6\",\"advertisingId\":\"RECON_AdvertiserId\",\"language\":\"en\",\"deviceOS\":\"Android\",\"externalFreeMemory\":45331,\"battery\":58,\"timestamp\":1489435970085,\"adUnit\":3,\"events\":[{\"provider\":\"AppLovin\",\"providerSDKVersion\":\"6.3.2\",\"providerAdapterVersion\":\"2.1.1\",\"sessionDepth\":1,\"eventId\":1,\"timestamp\":1489435970073},{\"provider\":\"Mediation\",\"sessionDepth\":1,\"eventId\":1,\"timestamp\":1489435969079},{\"provider\":\"Mediation\",\"status\":\"true\",\"sessionDepth\":1,\"eventId\":4,\"timestamp\":1489435969104}]}", 
        "protocol": "HTTPS", 
        "referrer": null, 
        "scr_port": 47939, 
        "src_ip": "-", 
        "tk_flag": null, 
        "ts": "1489435986002", 
        "uri": "/mediation/", 
        "user_agent": null
    }, 
    "1489436000201,59d62597-528a-4032-a0ca-aaff7586c709": {
        "domain": "", 
        "dst_ip": "54.225.193.240", 
        "dst_port": 443, 
        "headers": {
            "accept": "application/json", 
            "accept-encoding": "gzip", 
            "connection": "Keep-Alive", 
            "content-length": "1331", 
            "content-type": "application/json; charset=utf-8", 
            "host": "rpc.tapjoy.com", 
            "user-agent": "TapjoySDK 11.7.0 (Nexus 6; Android 7.0; en_US)"
        }, 
        "host": "rpc.tapjoy.com", 
        "is_foreground": false, 
        "is_host_ip": 0, 
        "label": 1, 
        "md5": null, 
        "method": "POST", 
        "package_name": "com.yodo1.crossyroad", 
        "package_version": "2.3.1", 
        "pii_types": [
            "AndroidId", 
            "AdvertiserId", 
            "AdvertiserId", 
            "AdvertiserId"
        ], 
        "platform": "android", 
        "post_body": "[{\"api_key\":\"WE9kKXRdgACAAHJGmQAFGAExCrazt0M1SIR31Rhdly1aMZCFLaikUA4x9BjD\",\"events\":[{\"meta\":{\"fq30_change\":\"fq30_0_1\",\"fq7_change\":\"fq7_0_1\"},\"time\":1489435971000,\"event_seq\":1,\"info\":{\"sdk\":\"11.7.0\\/Android\",\"display_h\":1440,\"device_maker\":\"motorola\",\"pkg_sign\":\"Pzqln2Fz5In6UD2u 4Syj\\/3yqhM=\",\"mac\":\"020000000000\",\"locale\":\"en_US\",\"timezone\":\"America\\/Los_Angeles\",\"os_ver\":\"7.0\",\"device_id\":\"RECON_AndroidId\",\"display_d\":560,\"country_sim\":\"GR\",\"device_model\":\"Nexus 6\",\"pkg_id\":\"com.yodo1.crossyroad\",\"country_net\":\"US\",\"display_w\":2392,\"os_name\":\"Android\"},\"name\":\"bootup\",\"systime\":1489435970422,\"app\":{\"pkg_ver\":\"2.3.1\",\"pkg_rev\":95},\"user\":{\"idfa\":\"RECON_AdvertiserId\",\"session\":{\"total_count\":1},\"fq7\":1,\"purchase\":{},\"fq30\":1,\"installed\":1489432871167},\"type\":\"app\"},{\"name\":\"install\",\"systime\":1489435971435,\"time\":1489435972013,\"event_prev\":{\"name\":\"bootup\",\"type\":\"app\"},\"event_seq\":2,\"type\":\"app\"},{\"time\":1489436000119,\"event_prev\":{\"name\":\"install\",\"type\":\"app\"},\"event_seq\":3,\"name\":\"session\",\"systime\":1489435999541,\"duration\":29070,\"type\":\"app\",\"user\":{\"session\":{\"total_length\":29070,\"total_count\":1},\"installed\":1489432871167,\"purchase\":{},\"idfa\":\"RECON_AdvertiserId\",\"user_id\":\"RECON_AdvertiserId\",\"fq7\":1,\"fq30\":1}}],\"debug\":true,\"sdk_ver\":\"11.7.0\\/Android\"}]", 
        "protocol": "HTTPS", 
        "referrer": null, 
        "scr_port": 47182, 
        "src_ip": "-", 
        "tk_flag": null, 
        "ts": "1489436000201", 
        "uri": "/api/v1/cevs", 
        "user_agent": null
    }
}