{
    "1489369966655,7c48dba8-0eb0-436c-b8b0-6658aa8327d0": {
        "domain": "", 
        "dst_ip": "52.41.164.204", 
        "dst_port": 443, 
        "headers": {
            "accept-encoding": "gzip", 
            "connection": "Keep-Alive", 
            "content-length": "481", 
            "content-type": "text/xml", 
            "host": "pssvc.iqzone.com", 
            "user-agent": "Dalvik/2.1.0 (Linux; U; Android 7.0; Nexus 6 Build/NBD91Y)"
        }, 
        "host": "pssvc.iqzone.com", 
        "is_foreground": true, 
        "is_host_ip": 0, 
        "label": 0, 
        "md5": null, 
        "method": "POST", 
        "package_name": "com.outfit7.tomlovesangelafree", 
        "package_version": "2.0.1", 
        "pii_types": null, 
        "platform": "android", 
        "post_body": "<soap:Envelope xmlns:soap=\"http://schemas.xmlsoap.org/soap/envelope/\" xmlns:xsi=\"http://www.w3.org/2001/XMLSchema-instance\" xmlns:xsd=\"http://www.w3.org/2001/XMLSchema\"><soap:Body><GetPostitialConfiguration xmlns=\"http://svc.picdial.com/WebServices/\"><r xmlns=\"http://svc.picdial.com/WebServices/GetPostitialConfigurationInput\" k=\"Y1MzaWt6REp2N1RucWt6RWlzSlJlaVdTS0U5a0Nsa1puZERtZ1dySEt0VDBYMWxF\" pi=\"177\" cv=\"STA-73\" i=\"0\"/></GetPostitialConfiguration></soap:Body></soap:Envelope>", 
        "protocol": "HTTPS", 
        "referrer": null, 
        "scr_port": 39781, 
        "src_ip": "-", 
        "tk_flag": null, 
        "ts": "1489369966655", 
        "uri": "/e.asmx", 
        "user_agent": null
    }, 
    "1489369967546,6b408826-6abe-4f27-bc08-6ab204db1acc": {
        "domain": "", 
        "dst_ip": "52.41.164.204", 
        "dst_port": 443, 
        "headers": {
            "accept-encoding": "gzip", 
            "connection": "Keep-Alive", 
            "content-length": "516", 
            "content-type": "text/xml", 
            "host": "pssvc.iqzone.com", 
            "user-agent": "Dalvik/2.1.0 (Linux; U; Android 7.0; Nexus 6 Build/NBD91Y)"
        }, 
        "host": "pssvc.iqzone.com", 
        "is_foreground": true, 
        "is_host_ip": 0, 
        "label": 0, 
        "md5": null, 
        "method": "POST", 
        "package_name": "com.outfit7.tomlovesangelafree", 
        "package_version": "2.0.1", 
        "pii_types": null, 
        "platform": "android", 
        "post_body": "<soap:Envelope xmlns:soap=\"http://schemas.xmlsoap.org/soap/envelope/\" xmlns:xsi=\"http://www.w3.org/2001/XMLSchema-instance\" xmlns:xsd=\"http://www.w3.org/2001/XMLSchema\"><soap:Body><GetPostitialConfiguration xmlns=\"http://svc.picdial.com/WebServices/\"><r xmlns=\"http://svc.picdial.com/WebServices/GetPostitialConfigurationInput\" k=\"Y1MzaWt6REp2N1RucWt6RWlzSlJlaVdTS0U5a0Nsa1puZERtZ1dySEt0VDBYMWxF\" pi=\"177\" cv=\"STA-73\" i=\"839d8090-078d-11e7-b89c-7de8fd7caccc\"/></GetPostitialConfiguration></soap:Body></soap:Envelope>", 
        "protocol": "HTTPS", 
        "referrer": null, 
        "scr_port": 39781, 
        "src_ip": "-", 
        "tk_flag": null, 
        "ts": "1489369967546", 
        "uri": "/e.asmx", 
        "user_agent": null
    }, 
    "1489369971924,542c6368-1758-475f-bb92-2d044c7a55eb": {
        "domain": "", 
        "dst_ip": "216.115.100.124", 
        "dst_port": 443, 
        "headers": {
            "accept-encoding": "gzip", 
            "connection": "Keep-Alive", 
            "host": "cdn.flurry.com", 
            "user-agent": "Dalvik/2.1.0 (Linux; U; Android 7.0; Nexus 6 Build/NBD91Y)"
        }, 
        "host": "cdn.flurry.com", 
        "is_foreground": true, 
        "is_host_ip": 0, 
        "label": 0, 
        "md5": null, 
        "method": "GET", 
        "package_name": "com.outfit7.tomlovesangelafree", 
        "package_version": "2.0.1", 
        "pii_types": null, 
        "platform": "android", 
        "post_body": null, 
        "protocol": "HTTPS", 
        "referrer": null, 
        "scr_port": 39670, 
        "src_ip": "-", 
        "tk_flag": null, 
        "ts": "1489369971924", 
        "uri": "/sdkAssets/videocontrols/v1/android.zip", 
        "user_agent": null
    }, 
    "1489369987317,23ab7402-6e16-4f9a-8602-11cadf0cbcb6": {
        "domain": "", 
        "dst_ip": "23.15.229.202", 
        "dst_port": 443, 
        "headers": {
            "accept": "image/webp,image/*,*/*;q=0.8", 
            "accept-encoding": "gzip, deflate", 
            "accept-language": "en-US", 
            "connection": "keep-alive", 
            "host": "sb.scorecardresearch.com", 
            "user-agent": "Mozilla/5.0 (Linux; Android 7.0; Nexus 6 Build/NBD91Y; wv) AppleWebKit/537.36 (KHTML, like Gecko) Version/4.0 Chrome/56.0.2924.87 Mobile Safari/537.36", 
            "x-requested-with": "com.outfit7.tomlovesangelafree"
        }, 
        "host": "sb.scorecardresearch.com", 
        "is_foreground": true, 
        "is_host_ip": 0, 
        "label": 0, 
        "md5": null, 
        "method": "GET", 
        "package_name": "com.outfit7.tomlovesangelafree", 
        "package_version": "2.0.1", 
        "pii_types": null, 
        "platform": "android", 
        "post_body": null, 
        "protocol": "HTTPS", 
        "referrer": null, 
        "scr_port": 37397, 
        "src_ip": "-", 
        "tk_flag": null, 
        "ts": "1489369987317", 
        "uri": "/p2?c1=8&c2=6034722&c3=7740745&c12=089845c0bff0cd885012921b98e10a26f935dbd8&ns_ap_it=e&ns_ap_pn=android&ns_ap_device=Nexus 6&rn=20170313015307", 
        "user_agent": null
    }, 
    "1489369987928,9ea22d73-14b6-4bf9-b212-4686a2983036": {
        "domain": "", 
        "dst_ip": "104.68.98.226", 
        "dst_port": 443, 
        "headers": {
            "accept": "*/*", 
            "accept-encoding": "gzip, deflate", 
            "accept-language": "en-US", 
            "connection": "keep-alive", 
            "host": "secure.cdn.fastclick.net", 
            "user-agent": "Mozilla/5.0 (Linux; Android 7.0; Nexus 6 Build/NBD91Y; wv) AppleWebKit/537.36 (KHTML, like Gecko) Version/4.0 Chrome/56.0.2924.87 Mobile Safari/537.36", 
            "x-requested-with": "com.outfit7.tomlovesangelafree"
        }, 
        "host": "secure.cdn.fastclick.net", 
        "is_foreground": true, 
        "is_host_ip": 0, 
        "label": 0, 
        "md5": null, 
        "method": "GET", 
        "package_name": "com.outfit7.tomlovesangelafree", 
        "package_version": "2.0.1", 
        "pii_types": null, 
        "platform": "android", 
        "post_body": null, 
        "protocol": "HTTPS", 
        "referrer": null, 
        "scr_port": 37661, 
        "src_ip": "-", 
        "tk_flag": null, 
        "ts": "1489369987928", 
        "uri": "/clients/jac/jac.js", 
        "user_agent": null
    }, 
    "1489369989408,7a648526-faab-47f2-97d0-ec8011b54d9b": {
        "domain": "", 
        "dst_ip": "104.68.98.226", 
        "dst_port": 443, 
        "headers": {
            "accept": "image/webp,image/*,*/*;q=0.8", 
            "accept-encoding": "gzip, deflate", 
            "accept-language": "en-US", 
            "connection": "keep-alive", 
            "host": "secure.cdn.fastclick.net", 
            "user-agent": "Mozilla/5.0 (Linux; Android 7.0; Nexus 6 Build/NBD91Y; wv) AppleWebKit/537.36 (KHTML, like Gecko) Version/4.0 Chrome/56.0.2924.87 Mobile Safari/537.36", 
            "x-requested-with": "com.outfit7.tomlovesangelafree"
        }, 
        "host": "secure.cdn.fastclick.net", 
        "is_foreground": true, 
        "is_host_ip": 0, 
        "label": 0, 
        "md5": null, 
        "method": "GET", 
        "package_name": "com.outfit7.tomlovesangelafree", 
        "package_version": "2.0.1", 
        "pii_types": null, 
        "platform": "android", 
        "post_body": null, 
        "protocol": "HTTPS", 
        "referrer": null, 
        "scr_port": 37661, 
        "src_ip": "-", 
        "tk_flag": null, 
        "ts": "1489369989408", 
        "uri": "/content/adv/aids/109/60109/media2103790.jpg", 
        "user_agent": null
    }, 
    "1489369990848,5e67ebc4-9f46-40f9-8ebb-d6ec6e16a4b8": {
        "domain": "", 
        "dst_ip": "64.156.167.95", 
        "dst_port": 443, 
        "headers": {
            "accept": "image/webp,image/*,*/*;q=0.8", 
            "accept-encoding": "gzip, deflate", 
            "accept-language": "en-US", 
            "connection": "keep-alive", 
            "host": "secure.fastclick.net", 
            "user-agent": "Mozilla/5.0 (Linux; Android 7.0; Nexus 6 Build/NBD91Y; wv) AppleWebKit/537.36 (KHTML, like Gecko) Version/4.0 Chrome/56.0.2924.87 Mobile Safari/537.36", 
            "x-requested-with": "com.outfit7.tomlovesangelafree"
        }, 
        "host": "secure.fastclick.net", 
        "is_foreground": true, 
        "is_host_ip": 0, 
        "label": 0, 
        "md5": null, 
        "method": "GET", 
        "package_name": "com.outfit7.tomlovesangelafree", 
        "package_version": "2.0.1", 
        "pii_types": null, 
        "platform": "android", 
        "post_body": null, 
        "protocol": "HTTPS", 
        "referrer": null, 
        "scr_port": 43822, 
        "src_ip": "-", 
        "tk_flag": null, 
        "ts": "1489369990848", 
        "uri": "/w/impix.cgi?ud=CcoZBldr0q0-EQAAAAAAAAAAGQAAAEDsfA8-IadAZmfRO-U_KAAwAVoSMzk2Mjk3NzM4MDAwNzM3NDkwaIP3l8YFehI0MjI0MDU5OTk4NTg0Mzg3OTGIAfv6hQGQAYj7oAWYAc6HBqABD6gBEeoBQDA7MTQzOzExOzE7MjAwOzIuMC4yLmNzczsyLjEuMC5qcztjb20ub3V0Zml0Ny50b21sb3Zlc2FuZ2VsYWZyZWXwAQCyAg4xNjkuMjM0LjQ3LjEzMNoCJGM3YmFiZjg4LTdiODQtNDVjNi1iNDM0LTA1NjE4N2Q4NTg3M-ACA5gDA6ADLg&sys=1&nozzle=11&upsid=396297738000737490", 
        "user_agent": null
    }, 
    "1489370010524,5c2e53fd-8790-4e47-90b4-364971fad924": {
        "domain": "", 
        "dst_ip": "23.15.229.202", 
        "dst_port": 443, 
        "headers": {
            "accept": "image/webp,image/*,*/*;q=0.8", 
            "accept-encoding": "gzip, deflate", 
            "accept-language": "en-US", 
            "connection": "keep-alive", 
            "host": "sb.scorecardresearch.com", 
            "user-agent": "Mozilla/5.0 (Linux; Android 7.0; Nexus 6 Build/NBD91Y; wv) AppleWebKit/537.36 (KHTML, like Gecko) Version/4.0 Chrome/56.0.2924.87 Mobile Safari/537.36", 
            "x-requested-with": "com.outfit7.tomlovesangelafree"
        }, 
        "host": "sb.scorecardresearch.com", 
        "is_foreground": true, 
        "is_host_ip": 0, 
        "label": 0, 
        "md5": null, 
        "method": "GET", 
        "package_name": "com.outfit7.tomlovesangelafree", 
        "package_version": "2.0.1", 
        "pii_types": null, 
        "platform": "android", 
        "post_body": null, 
        "protocol": "HTTPS", 
        "referrer": null, 
        "scr_port": 37466, 
        "src_ip": "-", 
        "tk_flag": null, 
        "ts": "1489370010524", 
        "uri": "/p2?c1=8&c2=6034722&c3=7740745&c12=089845c0bff0cd885012921b98e10a26f935dbd8&ns_ap_it=e&ns_ap_pn=android&ns_ap_device=Nexus 6&rn=20170313015311", 
        "user_agent": null
    }, 
    "1489370011380,9bb9d406-c4fc-4ad0-b5fa-f3fb3851b29f": {
        "domain": "", 
        "dst_ip": "64.156.167.95", 
        "dst_port": 443, 
        "headers": {
            "accept": "image/webp,image/*,*/*;q=0.8", 
            "accept-encoding": "gzip, deflate", 
            "accept-language": "en-US", 
            "connection": "keep-alive", 
            "cookie": "cttutcid=421482026615656583; pluto=396297738000737490|v1", 
            "host": "secure.fastclick.net", 
            "user-agent": "Mozilla/5.0 (Linux; Android 7.0; Nexus 6 Build/NBD91Y; wv) AppleWebKit/537.36 (KHTML, like Gecko) Version/4.0 Chrome/56.0.2924.87 Mobile Safari/537.36", 
            "x-requested-with": "com.outfit7.tomlovesangelafree"
        }, 
        "host": "secure.fastclick.net", 
        "is_foreground": true, 
        "is_host_ip": 0, 
        "label": 0, 
        "md5": null, 
        "method": "GET", 
        "package_name": "com.outfit7.tomlovesangelafree", 
        "package_version": "2.0.1", 
        "pii_types": null, 
        "platform": "android", 
        "post_body": null, 
        "protocol": "HTTPS", 
        "referrer": null, 
        "scr_port": 43881, 
        "src_ip": "-", 
        "tk_flag": null, 
        "ts": "1489370011380", 
        "uri": "/w/impix.cgi?ud=CT0e73Xz460-EQAAAAAAAAAAGQAAAEDsfA8-IadAZmfRO-U_KAAwAVoSMzk2Mjk3NzM4MDAwNzM3NDkwaIf3l8YFehI0MjM0NDc0MzQzNDg2ODgyOTmIAfv6hQGQAYj7oAWYAc6HBqABD6gBEeoBQDA7MTQzOzExOzE7MjAwOzIuMC4yLmNzczsyLjEuMC5qcztjb20ub3V0Zml0Ny50b21sb3Zlc2FuZ2VsYWZyZWXwAQCyAg4xNjkuMjM0LjQ3LjEzMNoCJGM3YmFiZjg4LTdiODQtNDVjNi1iNDM0LTA1NjE4N2Q4NTg3M-ACA5gDA6ADLg&sys=1&nozzle=11&upsid=396297738000737490", 
        "user_agent": null
    }, 
    "1489370013563,7de5a16e-715e-4079-a7bd-a6cb37d318f4": {
        "domain": "", 
        "dst_ip": "64.156.167.95", 
        "dst_port": 443, 
        "headers": {
            "accept": "text/html,application/xhtml+xml,application/xml;q=0.9,image/webp,*/*;q=0.8", 
            "accept-encoding": "gzip, deflate", 
            "accept-language": "en-US", 
            "connection": "keep-alive", 
            "cookie": "cttutcid=421482026615656583; pluto=396297738000737490|v1", 
            "host": "secure.fastclick.net", 
            "upgrade-insecure-requests": "1", 
            "user-agent": "Mozilla/5.0 (Linux; Android 7.0; Nexus 6 Build/NBD91Y; wv) AppleWebKit/537.36 (KHTML, like Gecko) Version/4.0 Chrome/56.0.2924.87 Mobile Safari/537.36", 
            "x-requested-with": "com.outfit7.tomlovesangelafree"
        }, 
        "host": "secure.fastclick.net", 
        "is_foreground": true, 
        "is_host_ip": 0, 
        "label": 1, 
        "md5": null, 
        "method": "GET", 
        "package_name": "com.outfit7.tomlovesangelafree", 
        "package_version": "2.0.1", 
        "pii_types": [
            "AdvertiserId"
        ], 
        "platform": "android", 
        "post_body": null, 
        "protocol": "HTTPS", 
        "referrer": null, 
        "scr_port": 43881, 
        "src_ip": "-", 
        "tk_flag": null, 
        "ts": "1489370013563", 
        "uri": "/w/click.here?cid=11025800&mid=2194811&m=15&sid=99278&c=0&tp=17&UD=WhIzOTYyOTc3MzgwMDA3Mzc0OTB6EjQyMzQ0NzQzNDM0ODY4ODI5OYgB_-qFAZABiPugBZgBzocGoAEPqAER6gFAMDsxNDM7MTE7MTsyMDA7Mi4wLjIuY3NzOzIuMS4wLmpzO2NvbS5vdXRmaXQ3LnRvbWxvdmVzYW5nZWxhZnJlZfABALICDjE2OS4yMzQuNDcuMTMw2gIkYzdiYWJmODgtN2I4NC00NWM2LWI0MzQtMDU2MTg3ZDg1ODcz8AIDmAMDoAMu&upsid=396297738000737490&sys=1&gaid=RECON_AdvertiserId", 
        "user_agent": null
    }
}