{
    "1489453740772,8726411b-254c-470f-95f9-3fd25da049f1": {
        "domain": "", 
        "dst_ip": "204.69.221.97", 
        "dst_port": 443, 
        "headers": {
            "accept-encoding": "gzip", 
            "accept-language": "en-US", 
            "connection": "Keep-Alive", 
            "content-length": "0", 
            "content-type": "application/x-www-form-urlencoded;", 
            "cookie": "firstVisit=5247936461105309381; adId=RECON_AdvertiserId; lUp=5247936461105309381; cUp=1", 
            "host": "reports.radiotime.com", 
            "user-agent": "TuneIn Radio/17.2 (Android 24; Nexus 6; Java)"
        }, 
        "host": "reports.radiotime.com", 
        "is_foreground": true, 
        "is_host_ip": 0, 
        "label": 1, 
        "md5": null, 
        "method": "POST", 
        "package_name": "tunein.player", 
        "package_version": "17.2", 
        "pii_types": [
            "AdvertiserId", 
            "Location", 
            "Location"
        ], 
        "platform": "android", 
        "post_body": null, 
        "protocol": "HTTPS", 
        "referrer": null, 
        "scr_port": 47394, 
        "src_ip": "-", 
        "tk_flag": null, 
        "ts": "1489453740772", 
        "uri": "/reports/a/r?R=f2451780-0e00-4206-b966-39d61149e472&N=mopub&F=320x50&L=banner&U=agltb3B1Yi1pbmNyDQsSBFNpdGUY2umjFAw&S=Home&partnerId=xwhZkVKi&serial=41077e19-91b8-47cf-bfc9-a4b410b97fe8&provider=ggl&version=17.2&con=wifi&device=phone&orientation=landscape&resolution=2392,1440&latlon=RECON_Location639640,RECON_Location842173", 
        "user_agent": null
    }, 
    "1489453740978,8dc5a7db-f629-4365-865e-9e2da7e845da": {
        "domain": "", 
        "dst_ip": "204.69.221.34", 
        "dst_port": 443, 
        "headers": {
            "accept-encoding": "gzip", 
            "accept-language": "en-US", 
            "connection": "Keep-Alive", 
            "content-length": "57", 
            "content-type": "application/x-www-form-urlencoded; charset=UTF-8", 
            "cookie": "firstVisit=5247936461105309381; adId=RECON_AdvertiserId; lUp=5247936461105309381; cUp=1", 
            "host": "opml.radiotime.com", 
            "user-agent": "TuneIn Radio/17.2 (Android 24; Nexus 6; Java)"
        }, 
        "host": "opml.radiotime.com", 
        "is_foreground": true, 
        "is_host_ip": 0, 
        "label": 1, 
        "md5": null, 
        "method": "POST", 
        "package_name": "tunein.player", 
        "package_version": "17.2", 
        "pii_types": [
            "AdvertiserId"
        ], 
        "platform": "android", 
        "post_body": "event=subscribe|cancel|upsellScreen.closeButton.true&", 
        "protocol": "HTTPS", 
        "referrer": null, 
        "scr_port": 44122, 
        "src_ip": "-", 
        "tk_flag": null, 
        "ts": "1489453740978", 
        "uri": "/Report.ashx?c=eventlist&device=PHONE&version=17.2&render=json&resolution=2392,1440&orientation=LANDSCAPE&partnerId=xwhZkVKi&provider=ggl&serial=41077e19-91b8-47cf-bfc9-a4b410b97fe8&con=wifi", 
        "user_agent": null
    }, 
    "1489453741009,6778db71-6a3d-48c8-aa76-9267668c3a5c": {
        "domain": "", 
        "dst_ip": "204.69.221.48", 
        "dst_port": 443, 
        "headers": {
            "accept-encoding": "gzip", 
            "accept-language": "en-US", 
            "connection": "Keep-Alive", 
            "cookie": "firstVisit=5247936461105309381; adId=RECON_AdvertiserId; lUp=5247936461105309381; cUp=1", 
            "host": "api.radiotime.com", 
            "user-agent": "TuneIn Radio/17.2 (Android 24; Nexus 6; Java)"
        }, 
        "host": "api.radiotime.com", 
        "is_foreground": true, 
        "is_host_ip": 0, 
        "label": 1, 
        "md5": null, 
        "method": "GET", 
        "package_name": "tunein.player", 
        "package_version": "17.2", 
        "pii_types": [
            "AdvertiserId", 
            "Location", 
            "Location"
        ], 
        "platform": "android", 
        "post_body": null, 
        "protocol": "HTTPS", 
        "referrer": null, 
        "scr_port": 46973, 
        "src_ip": "-", 
        "tk_flag": null, 
        "ts": "1489453741009", 
        "uri": "/categories/home?viewmodel=true&latlon=RECON_Location639640,RECON_Location842173&device=PHONE&version=17.2&render=json&resolution=2392,1440&orientation=LANDSCAPE&partnerId=xwhZkVKi&provider=ggl&serial=41077e19-91b8-47cf-bfc9-a4b410b97fe8&con=wifi", 
        "user_agent": null
    }, 
    "1489453741065,fe450e6b-d284-4693-b999-06651f28ccf7": {
        "domain": "", 
        "dst_ip": "52.50.243.153", 
        "dst_port": 443, 
        "headers": {
            "accept-encoding": "gzip", 
            "connection": "Keep-Alive", 
            "content-length": "1150", 
            "content-type": "application/json", 
            "host": "t.appsflyer.com", 
            "user-agent": "Dalvik/2.1.0 (Linux; U; Android 7.0; Nexus 6 Build/NBD91Y)"
        }, 
        "host": "t.appsflyer.com", 
        "is_foreground": true, 
        "is_host_ip": 0, 
        "label": 1, 
        "md5": null, 
        "method": "POST", 
        "package_name": "tunein.player", 
        "package_version": "17.2", 
        "pii_types": [
            "AdvertiserId"
        ], 
        "platform": "android", 
        "post_body": "[{\"device\":\"shamu\",\"installDate\":\"2017-03-13_162415-0700\",\"firstLaunchDate\":\"2017-03-13_162426-0700\",\"sdk\":\"24\",\"carrier\":\"T-Mobile\",\"deviceFingerPrintId\":\"00000000-5ddb-cdcf-ffff-ffffc12bc0cc\",\"date1\":\"2017-03-13_162415-0700\",\"af_preinstalled\":\"false\",\"advertiserIdEnabled\":\"true\",\"lang_code\":\"en\",\"appsflyerKey\":\"TFiNwHKRqFDNM89ja3WhoZ\",\"iaecounter\":\"0\",\"app_version_name\":\"17.2\",\"lang\":\"English\",\"timepassedsincelastlaunch\":\"5823\",\"advertiserId\":\"RECON_AdvertiserId\",\"isGaidWithGps\":\"true\",\"deviceData\":{\"build_display_id\":\"NBD91Y\",\"arch\":\"\",\"cpu_abi\":\"armeabi-v7a\",\"cpu_abi2\":\"armeabi\"},\"appUserId\":\"41077e19-91b8-47cf-bfc9-a4b410b97fe8\",\"af_v2\":\"63102e9cd597597b25fc34792a75d73a633adf5b\",\"deviceType\":\"user\",\"af_v\":\"395397126443b65935a8be3578ee7f4265624828\",\"app_version_code\":\"130500\",\"af_events_api\":\"1\",\"platformextension\":\"android_native\",\"network\":\"WIFI\",\"operator\":\"\",\"country\":\"US\",\"brand\":\"google\",\"date2\":\"2017-03-13_162415-0700\",\"af_timestamp\":\"1489453734327\",\"uid\":\"1489447455061-2490712762230032238\",\"isFirstCall\":\"false\",\"fb\":\"c80f006f-f5b4-4f1e-9b43-28a14d25adfe\",\"product\":\"shamu\",\"model\":\"Nexus 6\",\"counter\":\"4\"}]", 
        "protocol": "HTTPS", 
        "referrer": null, 
        "scr_port": 37048, 
        "src_ip": "-", 
        "tk_flag": null, 
        "ts": "1489453741065", 
        "uri": "/api/v4/androidevent?buildnumber=6.4&app_id=tunein.player", 
        "user_agent": null
    }, 
    "1489453741438,f8017b43-6126-4995-8067-30ad3761e0fb": {
        "domain": "", 
        "dst_ip": "52.50.243.153", 
        "dst_port": 443, 
        "headers": {
            "accept-encoding": "gzip", 
            "connection": "Keep-Alive", 
            "content-length": "1147", 
            "content-type": "application/json", 
            "host": "t.appsflyer.com", 
            "user-agent": "Dalvik/2.1.0 (Linux; U; Android 7.0; Nexus 6 Build/NBD91Y)"
        }, 
        "host": "t.appsflyer.com", 
        "is_foreground": true, 
        "is_host_ip": 0, 
        "label": 1, 
        "md5": null, 
        "method": "POST", 
        "package_name": "tunein.player", 
        "package_version": "17.2", 
        "pii_types": [
            "AdvertiserId"
        ], 
        "platform": "android", 
        "post_body": "[{\"device\":\"shamu\",\"installDate\":\"2017-03-13_162415-0700\",\"firstLaunchDate\":\"2017-03-13_162426-0700\",\"sdk\":\"24\",\"carrier\":\"T-Mobile\",\"deviceFingerPrintId\":\"00000000-5ddb-cdcf-ffff-ffffc12bc0cc\",\"date1\":\"2017-03-13_162415-0700\",\"af_preinstalled\":\"false\",\"advertiserIdEnabled\":\"true\",\"lang_code\":\"en\",\"appsflyerKey\":\"TFiNwHKRqFDNM89ja3WhoZ\",\"iaecounter\":\"0\",\"app_version_name\":\"17.2\",\"lang\":\"English\",\"timepassedsincelastlaunch\":\"4\",\"advertiserId\":\"RECON_AdvertiserId\",\"isGaidWithGps\":\"true\",\"deviceData\":{\"build_display_id\":\"NBD91Y\",\"arch\":\"\",\"cpu_abi\":\"armeabi-v7a\",\"cpu_abi2\":\"armeabi\"},\"appUserId\":\"41077e19-91b8-47cf-bfc9-a4b410b97fe8\",\"af_v2\":\"29e73fa36cb9a2d665a91933826025cf6486150e\",\"deviceType\":\"user\",\"af_v\":\"9c6e67d3d794235e77e7fda94b74f0dd831654bb\",\"app_version_code\":\"130500\",\"af_events_api\":\"1\",\"platformextension\":\"android_native\",\"network\":\"WIFI\",\"operator\":\"\",\"country\":\"US\",\"brand\":\"google\",\"date2\":\"2017-03-13_162415-0700\",\"af_timestamp\":\"1489453738556\",\"uid\":\"1489447455061-2490712762230032238\",\"isFirstCall\":\"false\",\"fb\":\"c80f006f-f5b4-4f1e-9b43-28a14d25adfe\",\"product\":\"shamu\",\"model\":\"Nexus 6\",\"counter\":\"5\"}]", 
        "protocol": "HTTPS", 
        "referrer": null, 
        "scr_port": 37052, 
        "src_ip": "-", 
        "tk_flag": null, 
        "ts": "1489453741438", 
        "uri": "/api/v4/androidevent?buildnumber=6.4&app_id=tunein.player", 
        "user_agent": null
    }, 
    "1489453741535,524aefa8-4cf5-4dbc-b07d-8bd2aca19552": {
        "domain": "", 
        "dst_ip": "204.69.221.34", 
        "dst_port": 443, 
        "headers": {
            "accept-encoding": "gzip", 
            "accept-language": "en-US", 
            "connection": "Keep-Alive", 
            "content-length": "41", 
            "content-type": "application/x-www-form-urlencoded; charset=UTF-8", 
            "cookie": "firstVisit=5247936461105309381; adId=RECON_AdvertiserId; lUp=5247936461105309381; cUp=1", 
            "host": "opml.radiotime.com", 
            "user-agent": "TuneIn Radio/17.2 (Android 24; Nexus 6; Java)"
        }, 
        "host": "opml.radiotime.com", 
        "is_foreground": true, 
        "is_host_ip": 0, 
        "label": 1, 
        "md5": null, 
        "method": "POST", 
        "package_name": "tunein.player", 
        "package_version": "17.2", 
        "pii_types": [
            "AdvertiserId", 
            "Location", 
            "Location"
        ], 
        "platform": "android", 
        "post_body": "event=subscribe|error|branch.timeout&", 
        "protocol": "HTTPS", 
        "referrer": null, 
        "scr_port": 44130, 
        "src_ip": "-", 
        "tk_flag": null, 
        "ts": "1489453741535", 
        "uri": "/Report.ashx?c=eventlist&latlon=RECON_Location639640,RECON_Location842173&device=PHONE&version=17.2&render=json&resolution=2392,1440&orientation=LANDSCAPE&partnerId=xwhZkVKi&provider=ggl&serial=41077e19-91b8-47cf-bfc9-a4b410b97fe8&con=wifi", 
        "user_agent": null
    }, 
    "1489453741574,0c050cdd-724a-4d19-9c48-6ff1eade7be7": {
        "domain": "", 
        "dst_ip": "204.69.221.34", 
        "dst_port": 443, 
        "headers": {
            "accept-encoding": "gzip", 
            "accept-language": "en-US", 
            "connection": "Keep-Alive", 
            "content-length": "60", 
            "content-type": "application/x-www-form-urlencoded; charset=UTF-8", 
            "cookie": "firstVisit=5247936461105309381; adId=RECON_AdvertiserId; lUp=5247936461105309381; cUp=1", 
            "host": "opml.radiotime.com", 
            "user-agent": "TuneIn Radio/17.2 (Android 24; Nexus 6; Java)"
        }, 
        "host": "opml.radiotime.com", 
        "is_foreground": true, 
        "is_host_ip": 0, 
        "label": 1, 
        "md5": null, 
        "method": "POST", 
        "package_name": "tunein.player", 
        "package_version": "17.2", 
        "pii_types": [
            "AdvertiserId"
        ], 
        "platform": "android", 
        "post_body": "event=subscribe|show|firstload.upsellvriskfree2buttonv4&", 
        "protocol": "HTTPS", 
        "referrer": null, 
        "scr_port": 44126, 
        "src_ip": "-", 
        "tk_flag": null, 
        "ts": "1489453741574", 
        "uri": "/Report.ashx?c=eventlist&device=PHONE&version=17.2&render=json&resolution=2392,1440&orientation=LANDSCAPE&partnerId=xwhZkVKi&provider=ggl&serial=41077e19-91b8-47cf-bfc9-a4b410b97fe8&con=wifi", 
        "user_agent": null
    }, 
    "1489453745457,01eae520-ff37-4469-9046-43f6352ed61f": {
        "domain": "", 
        "dst_ip": "204.69.221.97", 
        "dst_port": 443, 
        "headers": {
            "accept-encoding": "gzip", 
            "accept-language": "en-US", 
            "connection": "Keep-Alive", 
            "content-length": "0", 
            "content-type": "application/x-www-form-urlencoded;", 
            "cookie": "firstVisit=5247936461105309381; adId=RECON_AdvertiserId; lUp=5247936461105309381; cUp=1", 
            "host": "reports.radiotime.com", 
            "user-agent": "TuneIn Radio/17.2 (Android 24; Nexus 6; Java)"
        }, 
        "host": "reports.radiotime.com", 
        "is_foreground": true, 
        "is_host_ip": 0, 
        "label": 1, 
        "md5": null, 
        "method": "POST", 
        "package_name": "tunein.player", 
        "package_version": "17.2", 
        "pii_types": [
            "AdvertiserId", 
            "Location", 
            "Location"
        ], 
        "platform": "android", 
        "post_body": null, 
        "protocol": "HTTPS", 
        "referrer": null, 
        "scr_port": 47437, 
        "src_ip": "-", 
        "tk_flag": null, 
        "ts": "1489453745457", 
        "uri": "/reports/a/r?R=39972b99-dfad-40de-b036-35ccd4f5308c&N=mopub&F=320x50&L=banner&U=agltb3B1Yi1pbmNyDQsSBFNpdGUY2umjFAw&S=Profile&partnerId=xwhZkVKi&serial=41077e19-91b8-47cf-bfc9-a4b410b97fe8&provider=ggl&version=17.2&con=wifi&device=phone&orientation=landscape&resolution=2392,1440&latlon=RECON_Location639640,RECON_Location842173", 
        "user_agent": null
    }, 
    "1489453745742,7d62a52e-79d1-4259-9d7c-6b33ac4f2a6a": {
        "domain": "", 
        "dst_ip": "204.69.221.48", 
        "dst_port": 443, 
        "headers": {
            "accept-encoding": "gzip", 
            "accept-language": "en-US", 
            "connection": "Keep-Alive", 
            "cookie": "firstVisit=5247936461105309381; adId=RECON_AdvertiserId; lUp=5247936461105309381; cUp=1", 
            "host": "api.radiotime.com", 
            "user-agent": "TuneIn Radio/17.2 (Android 24; Nexus 6; Java)"
        }, 
        "host": "api.radiotime.com", 
        "is_foreground": true, 
        "is_host_ip": 0, 
        "label": 1, 
        "md5": null, 
        "method": "GET", 
        "package_name": "tunein.player", 
        "package_version": "17.2", 
        "pii_types": [
            "AdvertiserId", 
            "Location", 
            "Location"
        ], 
        "platform": "android", 
        "post_body": null, 
        "protocol": "HTTPS", 
        "referrer": null, 
        "scr_port": 47013, 
        "src_ip": "-", 
        "tk_flag": null, 
        "ts": "1489453745742", 
        "uri": "/profiles/s270276/contents?viewModel=true&itemToken=BhUVAwUABQABAAEAW1sMCeT1BQEVDFbk9QUMVuT1BUqGAAAAAAAA&latlon=RECON_Location639640,RECON_Location842173&device=PHONE&version=17.2&render=json&resolution=2392,1440&orientation=LANDSCAPE&partnerId=xwhZkVKi&provider=ggl&serial=41077e19-91b8-47cf-bfc9-a4b410b97fe8&con=wifi", 
        "user_agent": null
    }, 
    "1489453751560,2583cc9e-cfdb-46ec-97af-9fad2024d174": {
        "domain": "", 
        "dst_ip": "204.69.221.97", 
        "dst_port": 443, 
        "headers": {
            "accept-encoding": "gzip", 
            "accept-language": "en-US", 
            "connection": "Keep-Alive", 
            "content-length": "0", 
            "content-type": "application/x-www-form-urlencoded;", 
            "cookie": "firstVisit=5247936461105309381; adId=RECON_AdvertiserId; lUp=5247936461105309381; cUp=1", 
            "host": "reports.radiotime.com", 
            "user-agent": "TuneIn Radio/17.2 (Android 24; Nexus 6; Java)"
        }, 
        "host": "reports.radiotime.com", 
        "is_foreground": true, 
        "is_host_ip": 0, 
        "label": 1, 
        "md5": null, 
        "method": "POST", 
        "package_name": "tunein.player", 
        "package_version": "17.2", 
        "pii_types": [
            "AdvertiserId", 
            "Location", 
            "Location"
        ], 
        "platform": "android", 
        "post_body": null, 
        "protocol": "HTTPS", 
        "referrer": null, 
        "scr_port": 47449, 
        "src_ip": "-", 
        "tk_flag": null, 
        "ts": "1489453751560", 
        "uri": "/reports/a/f?R=39972b99-dfad-40de-b036-35ccd4f5308c&N=mopub&F=320x50&L=banner&U=agltb3B1Yi1pbmNyDQsSBFNpdGUY2umjFAw&S=Profile&T=6049&M=[tuneinadsdkv2] Request Canceled.&partnerId=xwhZkVKi&serial=41077e19-91b8-47cf-bfc9-a4b410b97fe8&provider=ggl&version=17.2&con=wifi&device=phone&orientation=landscape&resolution=2392,1440&latlon=RECON_Location639640,RECON_Location842173", 
        "user_agent": null
    }, 
    "1489453753904,d8b75510-416d-4fb5-a3c1-c832c7f32929": {
        "domain": "", 
        "dst_ip": "204.69.221.34", 
        "dst_port": 443, 
        "headers": {
            "accept-encoding": "gzip", 
            "accept-language": "en-US", 
            "connection": "Keep-Alive", 
            "content-length": "31", 
            "content-type": "application/x-www-form-urlencoded; charset=UTF-8", 
            "cookie": "firstVisit=5247936461105309381; adId=RECON_AdvertiserId; lUp=5247936461105309381; cUp=1", 
            "host": "opml.radiotime.com", 
            "user-agent": "TuneIn Radio/17.2 (Android 24; Nexus 6; Java)"
        }, 
        "host": "opml.radiotime.com", 
        "is_foreground": true, 
        "is_host_ip": 0, 
        "label": 1, 
        "md5": null, 
        "method": "POST", 
        "package_name": "tunein.player", 
        "package_version": "17.2", 
        "pii_types": [
            "AdvertiserId", 
            "Location", 
            "Location"
        ], 
        "platform": "android", 
        "post_body": "event=nowplaying|tap|sleep&", 
        "protocol": "HTTPS", 
        "referrer": null, 
        "scr_port": 44169, 
        "src_ip": "-", 
        "tk_flag": null, 
        "ts": "1489453753904", 
        "uri": "/Report.ashx?c=eventlist&latlon=RECON_Location639640,RECON_Location842173&device=PHONE&version=17.2&render=json&resolution=2392,1440&orientation=LANDSCAPE&partnerId=xwhZkVKi&provider=ggl&serial=41077e19-91b8-47cf-bfc9-a4b410b97fe8&con=wifi", 
        "user_agent": null
    }, 
    "1489453754085,74ac6df5-1682-42f3-9a34-44d9b4d425a2": {
        "domain": "", 
        "dst_ip": "204.69.221.97", 
        "dst_port": 443, 
        "headers": {
            "accept-encoding": "gzip", 
            "accept-language": "en-US", 
            "connection": "Keep-Alive", 
            "content-length": "0", 
            "content-type": "application/x-www-form-urlencoded;", 
            "cookie": "firstVisit=5247936461105309381; adId=RECON_AdvertiserId; lUp=5247936461105309381; cUp=1", 
            "host": "reports.radiotime.com", 
            "user-agent": "TuneIn Radio/17.2 (Android 24; Nexus 6; Java)"
        }, 
        "host": "reports.radiotime.com", 
        "is_foreground": true, 
        "is_host_ip": 0, 
        "label": 1, 
        "md5": null, 
        "method": "POST", 
        "package_name": "tunein.player", 
        "package_version": "17.2", 
        "pii_types": [
            "AdvertiserId", 
            "Location", 
            "Location"
        ], 
        "platform": "android", 
        "post_body": null, 
        "protocol": "HTTPS", 
        "referrer": null, 
        "scr_port": 47449, 
        "src_ip": "-", 
        "tk_flag": null, 
        "ts": "1489453754085", 
        "uri": "/reports/a/r?R=e0b78743-3d0e-4b0a-a0fb-3eb7262d4efe&N=mopub&F=320x50&L=banner&U=agltb3B1Yi1pbmNyDQsSBFNpdGUY2umjFAw&S=NowPlaying&partnerId=xwhZkVKi&serial=41077e19-91b8-47cf-bfc9-a4b410b97fe8&provider=ggl&version=17.2&con=wifi&device=phone&orientation=landscape&resolution=2392,1440&latlon=RECON_Location639640,RECON_Location842173", 
        "user_agent": null
    }, 
    "1489453754199,5130ccce-61f8-4303-8f29-a376c96f6ae1": {
        "domain": "", 
        "dst_ip": "204.69.221.34", 
        "dst_port": 443, 
        "headers": {
            "accept-encoding": "gzip", 
            "accept-language": "en-US", 
            "connection": "Keep-Alive", 
            "content-length": "31", 
            "content-type": "application/x-www-form-urlencoded; charset=UTF-8", 
            "cookie": "firstVisit=5247936461105309381; adId=RECON_AdvertiserId; lUp=5247936461105309381; cUp=1", 
            "host": "opml.radiotime.com", 
            "user-agent": "TuneIn Radio/17.2 (Android 24; Nexus 6; Java)"
        }, 
        "host": "opml.radiotime.com", 
        "is_foreground": true, 
        "is_host_ip": 0, 
        "label": 1, 
        "md5": null, 
        "method": "POST", 
        "package_name": "tunein.player", 
        "package_version": "17.2", 
        "pii_types": [
            "AdvertiserId", 
            "Location", 
            "Location"
        ], 
        "platform": "android", 
        "post_body": "event=nowplaying|tap|sleep&", 
        "protocol": "HTTPS", 
        "referrer": null, 
        "scr_port": 44171, 
        "src_ip": "-", 
        "tk_flag": null, 
        "ts": "1489453754199", 
        "uri": "/Report.ashx?c=eventlist&latlon=RECON_Location639640,RECON_Location842173&device=PHONE&version=17.2&render=json&resolution=2392,1440&orientation=LANDSCAPE&partnerId=xwhZkVKi&provider=ggl&serial=41077e19-91b8-47cf-bfc9-a4b410b97fe8&con=wifi", 
        "user_agent": null
    }, 
    "1489453756644,95063c5e-2e53-407f-b58a-fcc8f0cd494c": {
        "domain": "", 
        "dst_ip": "204.69.221.34", 
        "dst_port": 443, 
        "headers": {
            "accept-encoding": "gzip", 
            "accept-language": "en-US", 
            "connection": "Keep-Alive", 
            "cookie": "firstVisit=5247936461105309381; adId=RECON_AdvertiserId; lUp=5247936461105309381; cUp=1", 
            "host": "opml.radiotime.com", 
            "user-agent": "TuneIn Radio/17.2 (Android 24; Nexus 6; Java)"
        }, 
        "host": "opml.radiotime.com", 
        "is_foreground": true, 
        "is_host_ip": 0, 
        "label": 1, 
        "md5": null, 
        "method": "GET", 
        "package_name": "tunein.player", 
        "package_version": "17.2", 
        "pii_types": [
            "AdvertiserId", 
            "Location", 
            "Location"
        ], 
        "platform": "android", 
        "post_body": null, 
        "protocol": "HTTPS", 
        "referrer": null, 
        "scr_port": 44169, 
        "src_ip": "-", 
        "tk_flag": null, 
        "ts": "1489453756644", 
        "uri": "/Browse.ashx?latlon=RECON_Location639640,RECON_Location842173&device=PHONE&version=17.2&render=json&resolution=2392,1440&orientation=LANDSCAPE&partnerId=xwhZkVKi&provider=ggl&serial=41077e19-91b8-47cf-bfc9-a4b410b97fe8&con=wifi&c=presets", 
        "user_agent": null
    }, 
    "1489453760006,4c9de94e-0122-469d-8da9-f9b8be7ef9a8": {
        "domain": "", 
        "dst_ip": "204.69.221.97", 
        "dst_port": 443, 
        "headers": {
            "accept-encoding": "gzip", 
            "accept-language": "en-US", 
            "connection": "Keep-Alive", 
            "content-length": "0", 
            "content-type": "application/x-www-form-urlencoded;", 
            "cookie": "firstVisit=5247936461105309381; adId=RECON_AdvertiserId; lUp=5247936461105309381; cUp=1", 
            "host": "reports.radiotime.com", 
            "user-agent": "TuneIn Radio/17.2 (Android 24; Nexus 6; Java)"
        }, 
        "host": "reports.radiotime.com", 
        "is_foreground": true, 
        "is_host_ip": 0, 
        "label": 1, 
        "md5": null, 
        "method": "POST", 
        "package_name": "tunein.player", 
        "package_version": "17.2", 
        "pii_types": [
            "AdvertiserId", 
            "Location", 
            "Location"
        ], 
        "platform": "android", 
        "post_body": null, 
        "protocol": "HTTPS", 
        "referrer": null, 
        "scr_port": 47474, 
        "src_ip": "-", 
        "tk_flag": null, 
        "ts": "1489453760006", 
        "uri": "/reports/a/f?R=e0b78743-3d0e-4b0a-a0fb-3eb7262d4efe&N=mopub&F=320x50&L=banner&U=agltb3B1Yi1pbmNyDQsSBFNpdGUY2umjFAw&S=NowPlaying&T=5612&M=[tuneinadsdkv2] Request Canceled.&partnerId=xwhZkVKi&serial=41077e19-91b8-47cf-bfc9-a4b410b97fe8&provider=ggl&version=17.2&con=wifi&device=phone&orientation=landscape&resolution=2392,1440&latlon=RECON_Location639640,RECON_Location842173", 
        "user_agent": null
    }, 
    "1489453760205,76bd637d-b192-4f38-98f1-8fc7db8bb0b7": {
        "domain": "", 
        "dst_ip": "204.69.221.34", 
        "dst_port": 443, 
        "headers": {
            "accept-encoding": "gzip", 
            "accept-language": "en-US", 
            "connection": "Keep-Alive", 
            "content-length": "41", 
            "content-type": "application/x-www-form-urlencoded; charset=UTF-8", 
            "cookie": "firstVisit=5247936461105309381; adId=RECON_AdvertiserId; lUp=5247936461105309381; cUp=1", 
            "host": "opml.radiotime.com", 
            "user-agent": "TuneIn Radio/17.2 (Android 24; Nexus 6; Java)"
        }, 
        "host": "opml.radiotime.com", 
        "is_foreground": true, 
        "is_host_ip": 0, 
        "label": 1, 
        "md5": null, 
        "method": "POST", 
        "package_name": "tunein.player", 
        "package_version": "17.2", 
        "pii_types": [
            "AdvertiserId", 
            "Location", 
            "Location"
        ], 
        "platform": "android", 
        "post_body": "event=nowplaying|tap|moreInformation&", 
        "protocol": "HTTPS", 
        "referrer": null, 
        "scr_port": 44194, 
        "src_ip": "-", 
        "tk_flag": null, 
        "ts": "1489453760205", 
        "uri": "/Report.ashx?c=eventlist&latlon=RECON_Location639640,RECON_Location842173&device=PHONE&version=17.2&render=json&resolution=2392,1440&orientation=LANDSCAPE&partnerId=xwhZkVKi&provider=ggl&serial=41077e19-91b8-47cf-bfc9-a4b410b97fe8&con=wifi", 
        "user_agent": null
    }, 
    "1489453760321,91089f73-e7d9-498c-b045-a5d349b2b8b1": {
        "domain": "", 
        "dst_ip": "204.69.221.97", 
        "dst_port": 443, 
        "headers": {
            "accept-encoding": "gzip", 
            "accept-language": "en-US", 
            "connection": "Keep-Alive", 
            "content-length": "0", 
            "content-type": "application/x-www-form-urlencoded;", 
            "cookie": "firstVisit=5247936461105309381; adId=RECON_AdvertiserId; lUp=5247936461105309381; cUp=1", 
            "host": "reports.radiotime.com", 
            "user-agent": "TuneIn Radio/17.2 (Android 24; Nexus 6; Java)"
        }, 
        "host": "reports.radiotime.com", 
        "is_foreground": true, 
        "is_host_ip": 0, 
        "label": 1, 
        "md5": null, 
        "method": "POST", 
        "package_name": "tunein.player", 
        "package_version": "17.2", 
        "pii_types": [
            "AdvertiserId", 
            "Location", 
            "Location"
        ], 
        "platform": "android", 
        "post_body": null, 
        "protocol": "HTTPS", 
        "referrer": null, 
        "scr_port": 47476, 
        "src_ip": "-", 
        "tk_flag": null, 
        "ts": "1489453760321", 
        "uri": "/reports/a/r?R=1f5715a1-bba5-492d-aa0c-e467174d1e0b&N=mopub&F=320x50&L=banner&U=agltb3B1Yi1pbmNyDQsSBFNpdGUY2umjFAw&S=PlayerOptionsActivity&partnerId=xwhZkVKi&serial=41077e19-91b8-47cf-bfc9-a4b410b97fe8&provider=ggl&version=17.2&con=wifi&device=phone&orientation=landscape&resolution=2392,1440&latlon=RECON_Location639640,RECON_Location842173", 
        "user_agent": null
    }, 
    "1489453761635,d4b4b396-1aa8-4ac7-919b-d967ffc47a04": {
        "domain": "", 
        "dst_ip": "204.69.221.34", 
        "dst_port": 443, 
        "headers": {
            "accept-encoding": "gzip", 
            "accept-language": "en-US", 
            "connection": "Keep-Alive", 
            "content-length": "25", 
            "content-type": "application/x-www-form-urlencoded; charset=UTF-8", 
            "cookie": "firstVisit=5247936461105309381; adId=RECON_AdvertiserId; lUp=5247936461105309381; cUp=1", 
            "host": "opml.radiotime.com", 
            "user-agent": "TuneIn Radio/17.2 (Android 24; Nexus 6; Java)"
        }, 
        "host": "opml.radiotime.com", 
        "is_foreground": true, 
        "is_host_ip": 0, 
        "label": 1, 
        "md5": null, 
        "method": "POST", 
        "package_name": "tunein.player", 
        "package_version": "17.2", 
        "pii_types": [
            "AdvertiserId", 
            "Location", 
            "Location"
        ], 
        "platform": "android", 
        "post_body": "event=car|start|base&", 
        "protocol": "HTTPS", 
        "referrer": null, 
        "scr_port": 44194, 
        "src_ip": "-", 
        "tk_flag": null, 
        "ts": "1489453761635", 
        "uri": "/Report.ashx?c=eventlist&latlon=RECON_Location639640,RECON_Location842173&device=PHONE&version=17.2&render=json&resolution=2392,1440&orientation=LANDSCAPE&partnerId=xwhZkVKi&provider=ggl&serial=41077e19-91b8-47cf-bfc9-a4b410b97fe8&con=wifi", 
        "user_agent": null
    }, 
    "1489453762177,782f0588-b3c0-4670-aee2-60f164fae9b7": {
        "domain": "", 
        "dst_ip": "204.69.221.34", 
        "dst_port": 443, 
        "headers": {
            "accept-encoding": "gzip", 
            "accept-language": "en-US", 
            "connection": "Keep-Alive", 
            "cookie": "firstVisit=5247936461105309381; adId=RECON_AdvertiserId; lUp=5247936461105309381; cUp=1", 
            "host": "opml.radiotime.com", 
            "user-agent": "TuneIn Radio/17.2 (Android 24; Nexus 6; Java)"
        }, 
        "host": "opml.radiotime.com", 
        "is_foreground": true, 
        "is_host_ip": 0, 
        "label": 1, 
        "md5": null, 
        "method": "GET", 
        "package_name": "tunein.player", 
        "package_version": "17.2", 
        "pii_types": [
            "AdvertiserId", 
            "Location", 
            "Location"
        ], 
        "platform": "android", 
        "post_body": null, 
        "protocol": "HTTPS", 
        "referrer": null, 
        "scr_port": 44195, 
        "src_ip": "-", 
        "tk_flag": null, 
        "ts": "1489453762177", 
        "uri": "/Describe.ashx?latlon=RECON_Location639640,RECON_Location842173&device=PHONE&version=17.2&render=json&resolution=2392,1440&orientation=LANDSCAPE&partnerId=xwhZkVKi&provider=ggl&serial=41077e19-91b8-47cf-bfc9-a4b410b97fe8&con=wifi&id=s270276&c=composite&detail=options", 
        "user_agent": null
    }, 
    "1489453762284,7369230f-b4fc-43f6-b106-d3e5a1b3614e": {
        "domain": "", 
        "dst_ip": "204.69.221.97", 
        "dst_port": 443, 
        "headers": {
            "accept-encoding": "gzip", 
            "accept-language": "en-US", 
            "connection": "Keep-Alive", 
            "content-length": "0", 
            "content-type": "application/x-www-form-urlencoded;", 
            "cookie": "firstVisit=5247936461105309381; adId=RECON_AdvertiserId; lUp=5247936461105309381; cUp=1", 
            "host": "reports.radiotime.com", 
            "user-agent": "TuneIn Radio/17.2 (Android 24; Nexus 6; Java)"
        }, 
        "host": "reports.radiotime.com", 
        "is_foreground": true, 
        "is_host_ip": 0, 
        "label": 1, 
        "md5": null, 
        "method": "POST", 
        "package_name": "tunein.player", 
        "package_version": "17.2", 
        "pii_types": [
            "AdvertiserId", 
            "Location", 
            "Location"
        ], 
        "platform": "android", 
        "post_body": null, 
        "protocol": "HTTPS", 
        "referrer": null, 
        "scr_port": 47484, 
        "src_ip": "-", 
        "tk_flag": null, 
        "ts": "1489453762284", 
        "uri": "/reports/a/f?R=1f5715a1-bba5-492d-aa0c-e467174d1e0b&N=mopub&F=320x50&L=banner&U=agltb3B1Yi1pbmNyDQsSBFNpdGUY2umjFAw&S=PlayerOptionsActivity&T=625&M=[tuneinadsdkv2] Request Canceled.&partnerId=xwhZkVKi&serial=41077e19-91b8-47cf-bfc9-a4b410b97fe8&provider=ggl&version=17.2&con=wifi&device=phone&orientation=landscape&resolution=2392,1440&latlon=RECON_Location639640,RECON_Location842173", 
        "user_agent": null
    }, 
    "1489453764242,25446016-7f43-4110-8c12-ab80755c1026": {
        "domain": "", 
        "dst_ip": "204.69.221.34", 
        "dst_port": 443, 
        "headers": {
            "accept-encoding": "gzip", 
            "accept-language": "en-US", 
            "connection": "Keep-Alive", 
            "cookie": "firstVisit=5247936461105309381; adId=RECON_AdvertiserId; lUp=5247936461105309381; cUp=1", 
            "host": "opml.radiotime.com", 
            "user-agent": "TuneIn Radio/17.2 (Android 24; Nexus 6; Java)"
        }, 
        "host": "opml.radiotime.com", 
        "is_foreground": true, 
        "is_host_ip": 0, 
        "label": 1, 
        "md5": null, 
        "method": "GET", 
        "package_name": "tunein.player", 
        "package_version": "17.2", 
        "pii_types": [
            "AdvertiserId", 
            "Location", 
            "Location"
        ], 
        "platform": "android", 
        "post_body": null, 
        "protocol": "HTTPS", 
        "referrer": null, 
        "scr_port": 44194, 
        "src_ip": "-", 
        "tk_flag": null, 
        "ts": "1489453764242", 
        "uri": "/Browse.ashx?latlon=RECON_Location639640,RECON_Location842173&device=PHONE&mode=car&version=17.2&render=json&resolution=2392,1440&orientation=LANDSCAPE&partnerId=xwhZkVKi&provider=ggl&serial=41077e19-91b8-47cf-bfc9-a4b410b97fe8&con=wifi&c=best", 
        "user_agent": null
    }, 
    "1489453765059,48a25c03-0b09-42ff-a3dc-a17cfffae521": {
        "domain": "", 
        "dst_ip": "204.69.221.34", 
        "dst_port": 443, 
        "headers": {
            "accept-encoding": "gzip", 
            "accept-language": "en-US", 
            "connection": "Keep-Alive", 
            "cookie": "firstVisit=5247936461105309381; adId=RECON_AdvertiserId; lUp=5247936461105309381; cUp=1", 
            "host": "opml.radiotime.com", 
            "user-agent": "TuneIn Radio/17.2 (Android 24; Nexus 6; Java)"
        }, 
        "host": "opml.radiotime.com", 
        "is_foreground": true, 
        "is_host_ip": 0, 
        "label": 1, 
        "md5": null, 
        "method": "GET", 
        "package_name": "tunein.player", 
        "package_version": "17.2", 
        "pii_types": [
            "AdvertiserId", 
            "Location", 
            "Location"
        ], 
        "platform": "android", 
        "post_body": null, 
        "protocol": "HTTPS", 
        "referrer": null, 
        "scr_port": 44205, 
        "src_ip": "-", 
        "tk_flag": null, 
        "ts": "1489453765059", 
        "uri": "/Browse.ashx?latlon=RECON_Location639640,RECON_Location842173&device=PHONE&mode=car&version=17.2&render=json&resolution=2392,1440&orientation=LANDSCAPE&partnerId=xwhZkVKi&provider=ggl&serial=41077e19-91b8-47cf-bfc9-a4b410b97fe8&con=wifi&c=best", 
        "user_agent": null
    }, 
    "1489453766242,b0c82849-1952-4718-9c82-629e33481760": {
        "domain": "", 
        "dst_ip": "138.108.6.20", 
        "dst_port": 443, 
        "headers": {
            "accept-charset": "UTF-8", 
            "accept-encoding": "gzip", 
            "connection": "Keep-Alive", 
            "content-type": "text/plain", 
            "host": "secure-drm.imrworldwide.com", 
            "user-agent": "%%%4b4d2eb553f1830139a46a135501306f487f4255aff2864c4c100606065f92d0%%%", 
            "x-device-user-agent": "Dalvik/2.1.0 (Linux; U; Android 7.0; Nexus 6 Build/NBD91Y)"
        }, 
        "host": "secure-drm.imrworldwide.com", 
        "is_foreground": true, 
        "is_host_ip": 0, 
        "label": 0, 
        "md5": null, 
        "method": "GET", 
        "package_name": "tunein.player", 
        "package_version": "17.2", 
        "pii_types": null, 
        "platform": "android", 
        "post_body": null, 
        "protocol": "HTTPS", 
        "referrer": null, 
        "scr_port": 42791, 
        "src_ip": "-", 
        "tk_flag": null, 
        "ts": "1489453766242", 
        "uri": "/cgi-bin/cfg?cfgv=300&bldv=aa.5.1.1.3&apid=PDD6EA2AC-BEF4-4963-825C-99787C9B5ADC&apv=17.2.130500&apn=TuneIn Radio&bid=tunein.player&sdkv=aa.5.1.1&nuid=4b4d2eb553f1830139a46a135501306f487f4255aff2864c4c100606065f92d0&osver=ANDROID.7.0&devtypid=motorola-Nexus-6&devid=97f34917086504f9e7f1519d59d92eeffd1af3684b3d99b8227bce7192b3567a&enc=true&fmt=json&adf=&uoo=&longitude=&latitude=&tz=-25200&locale=en_US&lang=en&dma=&sfcode=drm&ccode=1&sendTime=1489453759&rnd=1489453759239", 
        "user_agent": null
    }, 
    "1489453773008,0af4e377-c162-489e-a1b0-022a2870c926": {
        "domain": "", 
        "dst_ip": "204.69.221.34", 
        "dst_port": 443, 
        "headers": {
            "accept-encoding": "gzip", 
            "accept-language": "en-US", 
            "connection": "Keep-Alive", 
            "content-length": "26", 
            "content-type": "application/x-www-form-urlencoded; charset=UTF-8", 
            "cookie": "firstVisit=5247936461105309381; adId=RECON_AdvertiserId; lUp=5247936461105309381; cUp=1", 
            "host": "opml.radiotime.com", 
            "user-agent": "TuneIn Radio/17.2 (Android 24; Nexus 6; Java)"
        }, 
        "host": "opml.radiotime.com", 
        "is_foreground": true, 
        "is_host_ip": 0, 
        "label": 1, 
        "md5": null, 
        "method": "POST", 
        "package_name": "tunein.player", 
        "package_version": "17.2", 
        "pii_types": [
            "AdvertiserId", 
            "Location", 
            "Location"
        ], 
        "platform": "android", 
        "post_body": "event=play|start|play&", 
        "protocol": "HTTPS", 
        "referrer": null, 
        "scr_port": 44215, 
        "src_ip": "-", 
        "tk_flag": null, 
        "ts": "1489453773008", 
        "uri": "/Report.ashx?c=eventlist&id=s35148&latlon=RECON_Location639640,RECON_Location842173&device=PHONE&mode=car&version=17.2&render=json&resolution=2392,1440&orientation=LANDSCAPE&partnerId=xwhZkVKi&provider=ggl&serial=41077e19-91b8-47cf-bfc9-a4b410b97fe8&con=wifi", 
        "user_agent": null
    }, 
    "1489453773951,9f2f46e8-1825-47cd-ab89-2764aa643c4c": {
        "domain": "", 
        "dst_ip": "204.69.221.34", 
        "dst_port": 443, 
        "headers": {
            "accept-encoding": "gzip", 
            "accept-language": "en-US", 
            "connection": "Keep-Alive", 
            "content-length": "26", 
            "content-type": "application/x-www-form-urlencoded; charset=UTF-8", 
            "cookie": "firstVisit=5247936461105309381; adId=RECON_AdvertiserId; lUp=5247936461105309381; cUp=1", 
            "host": "opml.radiotime.com", 
            "user-agent": "TuneIn Radio/17.2 (Android 24; Nexus 6; Java)"
        }, 
        "host": "opml.radiotime.com", 
        "is_foreground": true, 
        "is_host_ip": 0, 
        "label": 1, 
        "md5": null, 
        "method": "POST", 
        "package_name": "tunein.player", 
        "package_version": "17.2", 
        "pii_types": [
            "AdvertiserId", 
            "Location", 
            "Location"
        ], 
        "platform": "android", 
        "post_body": "event=play|start|play&", 
        "protocol": "HTTPS", 
        "referrer": null, 
        "scr_port": 44217, 
        "src_ip": "-", 
        "tk_flag": null, 
        "ts": "1489453773951", 
        "uri": "/Report.ashx?c=eventlist&id=s34635&latlon=RECON_Location639640,RECON_Location842173&device=PHONE&mode=car&version=17.2&render=json&resolution=2392,1440&orientation=LANDSCAPE&partnerId=xwhZkVKi&provider=ggl&serial=41077e19-91b8-47cf-bfc9-a4b410b97fe8&con=wifi", 
        "user_agent": null
    }, 
    "1489453783318,87f67cfd-c0cc-4142-bad3-a5977e0d5aee": {
        "domain": "", 
        "dst_ip": "54.72.150.199", 
        "dst_port": 443, 
        "headers": {
            "accept-encoding": "gzip", 
            "connection": "Keep-Alive", 
            "content-length": "413", 
            "content-type": "application/json", 
            "host": "stats.appsflyer.com", 
            "user-agent": "Dalvik/2.1.0 (Linux; U; Android 7.0; Nexus 6 Build/NBD91Y)"
        }, 
        "host": "stats.appsflyer.com", 
        "is_foreground": false, 
        "is_host_ip": 0, 
        "label": 1, 
        "md5": null, 
        "method": "POST", 
        "package_name": "tunein.player", 
        "package_version": "17.2", 
        "pii_types": [
            "AdvertiserId"
        ], 
        "platform": "android", 
        "post_body": "[{\"platform\":\"Android\",\"advertiserId\":\"RECON_AdvertiserId\",\"gcd_conversion_data_timing\":\"0\",\"devkey\":\"TFiNwHKRqFDNM89ja3WhoZ\",\"statType\":\"user_closed_app\",\"time_in_app\":\"41\",\"originalAppsflyerId\":\"1489447455061-2490712762230032238\",\"app_id\":\"tunein.player\",\"deviceFingerPrintId\":\"00000000-5ddb-cdcf-ffff-ffffc12bc0cc\",\"uid\":\"1489447455061-2490712762230032238\",\"channel\":null,\"launch_counter\":\"5\"}]", 
        "protocol": "HTTPS", 
        "referrer": null, 
        "scr_port": 40023, 
        "src_ip": "-", 
        "tk_flag": null, 
        "ts": "1489453783318", 
        "uri": "/stats", 
        "user_agent": null
    }, 
    "1489455031808,78aaef4d-3b23-4f97-bee9-b35aa8f2f5b8": {
        "domain": "", 
        "dst_ip": "23.23.144.49", 
        "dst_port": 443, 
        "headers": {
            "accept": "application/json", 
            "accept-encoding": "gzip", 
            "connection": "Keep-Alive", 
            "host": "settings.crashlytics.com", 
            "user-agent": "Crashlytics Android SDK/1.3.10.97", 
            "x-crashlytics-advertising-token": "RECON_AdvertiserId", 
            "x-crashlytics-android-id": "RECON_AndroidId", 
            "x-crashlytics-api-client-type": "android", 
            "x-crashlytics-api-client-version": "1.3.10.97", 
            "x-crashlytics-api-key": "a2dec7961f4a9ba3f3b9e5645916efde255703a6", 
            "x-crashlytics-developer-token": "470fa2b4ae81cd56ecbcda9735803434cec591fa", 
            "x-crashlytics-device-model": "motorola/Nexus 6", 
            "x-crashlytics-installation-id": "ca38442eb19e47229d59d5e2ecdc0301", 
            "x-crashlytics-os-build-version": "3578881", 
            "x-crashlytics-os-display-version": "7.0"
        }, 
        "host": "settings.crashlytics.com", 
        "is_foreground": false, 
        "is_host_ip": 0, 
        "label": 1, 
        "md5": null, 
        "method": "GET", 
        "package_name": "tunein.player", 
        "package_version": "17.2", 
        "pii_types": [
            "AdvertiserId", 
            "AndroidId"
        ], 
        "platform": "android", 
        "post_body": null, 
        "protocol": "HTTPS", 
        "referrer": null, 
        "scr_port": 45095, 
        "src_ip": "-", 
        "tk_flag": null, 
        "ts": "1489455031808", 
        "uri": "/spi/v2/platforms/android/apps/tunein.player/settings?icon_hash=3ab73b5564573ad45ac56ff528f32e48f7b8a8ad&display_version=17.2&source=1&instance=83889f560d09a6ddbd6cd9aa1e1b72b6a9f73fee&build_version=130500", 
        "user_agent": null
    }
}