{
    "1488840100897,1b23a4be-d1b7-4dee-851b-462d077965a0": {
        "domain": "", 
        "dst_ip": "130.211.14.80", 
        "dst_port": 443, 
        "headers": {
            "Accept-Encoding": "gzip", 
            "Connection": "Keep-Alive", 
            "Host": "pgorelease.nianticlabs.com", 
            "User-Agent": "Dalvik/2.1.0 (Linux; U; Android 7.0; Nexus 6 Build/NBD91Y)", 
            "X-Unity-Version": "5.5.1f1"
        }, 
        "host": "pgorelease.nianticlabs.com", 
        "is_foreground": false, 
        "is_host_ip": 0, 
        "label": 0, 
        "md5": null, 
        "method": "GET", 
        "package_name": "com.nianticlabs.pokemongo", 
        "package_version": "0.57.4", 
        "pii_types": null, 
        "platform": "android", 
        "post_body": null, 
        "protocol": "HTTPS", 
        "referrer": null, 
        "scr_port": 46122, 
        "src_ip": "-", 
        "tk_flag": null, 
        "ts": "1488840100897", 
        "uri": "/plfe/version", 
        "user_agent": "Dalvik/2.1.0 (Linux; U; Android 7.0; Nexus 6 Build/NBD91Y)"
    }, 
    "1488840131651,d4fc065d-e45d-4b16-8a58-f5843654e368": {
        "domain": "", 
        "dst_ip": "169.44.145.204", 
        "dst_port": 443, 
        "headers": {
            "Accept-Encoding": "gzip", 
            "Connection": "close", 
            "Content-Length": "980", 
            "Content-Type": "application/json", 
            "Host": "bootstrap.upsight-api.com", 
            "User-Agent": "Android-24", 
            "X-US-Ref-Id": "38c6d200-175f-43d7-8511-3d1bb7d1bd12"
        }, 
        "host": "bootstrap.upsight-api.com", 
        "is_foreground": true, 
        "is_host_ip": 0, 
        "label": 0, 
        "md5": null, 
        "method": "POST", 
        "package_name": "com.nianticlabs.pokemongo", 
        "package_version": "0.57.4", 
        "pii_types": null, 
        "platform": "android", 
        "post_body": "[{\"app.version\":\"0.57.4\",\"app.token\":\"a9cc12f87adc420baf964f187672ecb4\",\"opt_out\":false,\"sid\":\"2360887839511745659\",\"device.carrier\":\"T-Mobile\",\"device.os_version\":\"7.0 24\",\"request_ts\":1488840131,\"device.limit_ad_tracking\":false,\"bundle.schema_hash\":\"97d170e1550eee4afc0af065b78cda302a97674c\",\"device.type\":\"phone\",\"device.manufacturer\":\"motorola\",\"sdk.version\":\"4.2.5\",\"device.jailbroken\":false,\"locale\":\"en_US\",\"device.hardware\":\"Nexus 6\",\"screen.scale\":1.0,\"device.connection\":\"WIFI\",\"screen.dpi\":560,\"sessions\":[{\"install_ts\":1488840130,\"past_session_time\":0,\"events\":[{\"user_attributes\":{\"player_avatar\":0,\"item_count\":54,\"player_level\":1,\"pokecoin\":0,\"player_xp\":0,\"pokemon_count\":0},\"pub_data\":{},\"seq_id\":6,\"ts\":1488840131,\"type\":\"upsight.config.expired\",\"upsight_data\":{}}]}],\"screen.width\":1440,\"screen.height\":2392,\"location.tz\":\"-0800\",\"sdk.build\":\"cb.6+release.b16eeaa\",\"device.os\":\"android\",\"sdk.plugin\":\"unity:4.2.5-cb.6\",\"app.bundleid\":\"com.nianticlabs.pokemongo\"}]", 
        "protocol": "HTTPS", 
        "referrer": null, 
        "scr_port": 49392, 
        "src_ip": "-", 
        "tk_flag": null, 
        "ts": "1488840131651", 
        "uri": "/config/v1/a9cc12f87adc420baf964f187672ecb4/", 
        "user_agent": "Android-24"
    }, 
    "1488840132224,9465930d-74d1-482a-aeed-79f56e7979ab": {
        "domain": "", 
        "dst_ip": "169.44.145.200", 
        "dst_port": 443, 
        "headers": {
            "Accept-Encoding": "gzip", 
            "Connection": "close", 
            "Content-Length": "1228", 
            "Content-Type": "application/json", 
            "Host": "single.upsight-api.com", 
            "User-Agent": "Android-24", 
            "X-US-Ref-Id": "fc152b35-bd32-4532-a315-10cdc77e4728"
        }, 
        "host": "single.upsight-api.com", 
        "is_foreground": true, 
        "is_host_ip": 0, 
        "label": 1, 
        "md5": null, 
        "method": "POST", 
        "package_name": "com.nianticlabs.pokemongo", 
        "package_version": "0.57.4", 
        "pii_types": [
            "AndroidId"
        ], 
        "platform": "android", 
        "post_body": "[{\"app.version\":\"0.57.4\",\"app.token\":\"a9cc12f87adc420baf964f187672ecb4\",\"opt_out\":false,\"sid\":\"2360887839511745659\",\"identifiers\":\"pub\",\"device.os_version\":\"7.0 24\",\"device.carrier\":\"T-Mobile\",\"request_ts\":1488840131,\"device.limit_ad_tracking\":false,\"device.manufacturer\":\"motorola\",\"device.type\":\"phone\",\"bundle.schema_hash\":\"97d170e1550eee4afc0af065b78cda302a97674c\",\"sdk.version\":\"4.2.5\",\"device.jailbroken\":false,\"locale\":\"en_US\",\"device.hardware\":\"Nexus 6\",\"screen.scale\":1.0,\"device.connection\":\"WIFI\",\"screen.dpi\":560,\"sessions\":[{\"session_start\":1488840130,\"install_ts\":1488840130,\"past_session_time\":0,\"session_num\":1,\"events\":[{\"user_attributes\":{\"player_avatar\":0,\"item_count\":54,\"player_level\":1,\"pokecoin\":0,\"player_xp\":0,\"pokemon_count\":0},\"pub_data\":{},\"seq_id\":5,\"ts\":1488840130,\"type\":\"upsight.comm.register\",\"upsight_data\":{\"token\":\"APA91bGkbryN5917jjyxSpi2rvw7bO-MQ3aKbjrixjByY79ZVammMFX_vJzf5NSnYP2cDshZkJOne-gcJDRXs7sarTGKeyuu2jPea8YRAqjD8ql0hiCtbPNM-H8nlqFTfL0hTKD5wsv4\"}}]}],\"screen.width\":1440,\"screen.height\":2392,\"location.tz\":\"-0800\",\"sdk.build\":\"cb.6+release.b16eeaa\",\"sdk.plugin\":\"unity:4.2.5-cb.6\",\"device.os\":\"android\",\"ids.android_id\":\"RECON_AndroidId\",\"app.bundleid\":\"com.nianticlabs.pokemongo\"}]", 
        "protocol": "HTTPS", 
        "referrer": null, 
        "scr_port": 47839, 
        "src_ip": "-", 
        "tk_flag": null, 
        "ts": "1488840132224", 
        "uri": "/sdk/v1/events/a9cc12f87adc420baf964f187672ecb4/", 
        "user_agent": "Android-24"
    }, 
    "1488840132527,9f886d22-c027-441c-a18a-b5522127cf96": {
        "domain": "", 
        "dst_ip": "169.44.145.200", 
        "dst_port": 443, 
        "headers": {
            "Accept-Encoding": "gzip", 
            "Connection": "close", 
            "Content-Length": "1077", 
            "Content-Type": "application/json", 
            "Host": "single.upsight-api.com", 
            "User-Agent": "Android-24", 
            "X-US-Ref-Id": "85c132c0-b815-44d9-96c4-4a4d397abdb7"
        }, 
        "host": "single.upsight-api.com", 
        "is_foreground": true, 
        "is_host_ip": 0, 
        "label": 1, 
        "md5": null, 
        "method": "POST", 
        "package_name": "com.nianticlabs.pokemongo", 
        "package_version": "0.57.4", 
        "pii_types": [
            "AndroidId"
        ], 
        "platform": "android", 
        "post_body": "[{\"app.version\":\"0.57.4\",\"app.token\":\"a9cc12f87adc420baf964f187672ecb4\",\"opt_out\":false,\"sid\":\"2360887839511745659\",\"identifiers\":\"pub\",\"device.os_version\":\"7.0 24\",\"device.carrier\":\"T-Mobile\",\"request_ts\":1488840132,\"device.limit_ad_tracking\":false,\"device.manufacturer\":\"motorola\",\"device.type\":\"phone\",\"bundle.schema_hash\":\"97d170e1550eee4afc0af065b78cda302a97674c\",\"sdk.version\":\"4.2.5\",\"device.jailbroken\":false,\"locale\":\"en_US\",\"device.hardware\":\"Nexus 6\",\"screen.scale\":1.0,\"device.connection\":\"WIFI\",\"screen.dpi\":560,\"sessions\":[{\"session_start\":1488840130,\"install_ts\":1488840130,\"past_session_time\":0,\"session_num\":1,\"events\":[{\"user_attributes\":{\"player_avatar\":0,\"item_count\":0,\"player_level\":0,\"pokecoin\":0,\"player_xp\":0,\"pokemon_count\":0},\"pub_data\":{},\"seq_id\":1,\"ts\":1488840130,\"type\":\"upsight.session.start\",\"upsight_data\":{}}]}],\"screen.width\":1440,\"screen.height\":2392,\"location.tz\":\"-0800\",\"sdk.build\":\"cb.6+release.b16eeaa\",\"sdk.plugin\":\"unity:4.2.5-cb.6\",\"device.os\":\"android\",\"ids.android_id\":\"RECON_AndroidId\",\"app.bundleid\":\"com.nianticlabs.pokemongo\"}]", 
        "protocol": "HTTPS", 
        "referrer": null, 
        "scr_port": 47842, 
        "src_ip": "-", 
        "tk_flag": null, 
        "ts": "1488840132527", 
        "uri": "/sdk/v1/events/a9cc12f87adc420baf964f187672ecb4/", 
        "user_agent": "Android-24"
    }, 
    "1488840195049,9cb05718-ef44-4876-90d1-4228affad6f5": {
        "domain": "", 
        "dst_ip": "74.125.28.128", 
        "dst_port": 443, 
        "headers": {
            "Accept-Encoding": "gzip", 
            "Connection": "Keep-Alive", 
            "Host": "storage.googleapis.com", 
            "User-Agent": "Dalvik/2.1.0 (Linux; U; Android 7.0; Nexus 6 Build/NBD91Y)", 
            "X-Unity-Version": "5.5.1f1"
        }, 
        "host": "storage.googleapis.com", 
        "is_foreground": false, 
        "is_host_ip": 0, 
        "label": 0, 
        "md5": null, 
        "method": "GET", 
        "package_name": "com.nianticlabs.pokemongo", 
        "package_version": "0.57.4", 
        "pii_types": null, 
        "platform": "android", 
        "post_body": null, 
        "protocol": "HTTPS", 
        "referrer": null, 
        "scr_port": 40513, 
        "src_ip": "-", 
        "tk_flag": null, 
        "ts": "1488840195049", 
        "uri": "/cloud_assets_pgorelease/bundles/android/f_hat_default_b_bundle_icon?generation=1487049532480000&GoogleAccessId=pgorelease-service-account@pgorelease.iam.gserviceaccount.com&Expires=1488840495&Signature=XORgsqh7AqVCOTsSlnkHI6ElJ4dik7vrCR2XjLFbDsiSHABuIoq/m2RE6JWE8u9Pk5JSx622vsJWSh+mhJBDJTKGTLXTSGNuiZdqzMksejkff5cwpkXIFjZXQAI9TFUHg38zW/2/Gpu+iaVyf3f9NvM2GJROpQI2PLmJjM7HZmJglEwaJRbmaSlwdvY75Ga2LSXeBciMe/zGceQepw9gXfl5vLaN5dj98m/ctS2Mi9ShbirpEYftGdij7ZWqkCFNzYbYLDfBTn2r186+YWRj9UkW/Nan4W8rwYs+klZBCrwFyMO6ZFZXbd0jT+Jm1RpNF+QxHkWG+pvGTaY7Q/9y1g==", 
        "user_agent": "Dalvik/2.1.0 (Linux; U; Android 7.0; Nexus 6 Build/NBD91Y)"
    }, 
    "1488840251890,6f644c47-2a2d-4f06-9fa8-8e23b6aa8915": {
        "domain": "", 
        "dst_ip": "169.44.145.213", 
        "dst_port": 443, 
        "headers": {
            "Accept-Encoding": "gzip", 
            "Connection": "close", 
            "Content-Length": "1037", 
            "Content-Type": "application/json", 
            "Host": "bootstrap.upsight-api.com", 
            "User-Agent": "Android-24", 
            "X-US-Ref-Id": "43fdae6e-b98f-4a7d-8630-3f62b2c62c59"
        }, 
        "host": "bootstrap.upsight-api.com", 
        "is_foreground": true, 
        "is_host_ip": 0, 
        "label": 1, 
        "md5": null, 
        "method": "POST", 
        "package_name": "com.nianticlabs.pokemongo", 
        "package_version": "0.57.4", 
        "pii_types": [
            "AndroidId"
        ], 
        "platform": "android", 
        "post_body": "[{\"app.version\":\"0.57.4\",\"app.token\":\"a9cc12f87adc420baf964f187672ecb4\",\"opt_out\":false,\"sid\":\"2360887839511745659\",\"identifiers\":\"pub\",\"device.os_version\":\"7.0 24\",\"device.carrier\":\"T-Mobile\",\"request_ts\":1488840251,\"device.limit_ad_tracking\":false,\"device.manufacturer\":\"motorola\",\"device.type\":\"phone\",\"bundle.schema_hash\":\"97d170e1550eee4afc0af065b78cda302a97674c\",\"sdk.version\":\"4.2.5\",\"device.jailbroken\":false,\"locale\":\"en_US\",\"device.hardware\":\"Nexus 6\",\"screen.scale\":1.0,\"device.connection\":\"WIFI\",\"screen.dpi\":560,\"sessions\":[{\"install_ts\":1488840130,\"past_session_time\":0,\"events\":[{\"user_attributes\":{\"player_avatar\":0,\"item_count\":54,\"player_level\":1,\"pokecoin\":0,\"player_xp\":0,\"pokemon_count\":0},\"pub_data\":{},\"seq_id\":35,\"ts\":1488840251,\"type\":\"upsight.config.expired\",\"upsight_data\":{}}]}],\"screen.width\":1440,\"screen.height\":2392,\"location.tz\":\"-0800\",\"sdk.build\":\"cb.6+release.b16eeaa\",\"sdk.plugin\":\"unity:4.2.5-cb.6\",\"device.os\":\"android\",\"ids.android_id\":\"RECON_AndroidId\",\"app.bundleid\":\"com.nianticlabs.pokemongo\"}]", 
        "protocol": "HTTPS", 
        "referrer": null, 
        "scr_port": 43016, 
        "src_ip": "-", 
        "tk_flag": null, 
        "ts": "1488840251890", 
        "uri": "/config/v1/a9cc12f87adc420baf964f187672ecb4/", 
        "user_agent": "Android-24"
    }, 
    "1488840253304,0089774d-3ad3-40bf-87de-8cc767d7c7ac": {
        "domain": "", 
        "dst_ip": "169.46.12.93", 
        "dst_port": 443, 
        "headers": {
            "Accept-Encoding": "gzip", 
            "Connection": "close", 
            "Content-Length": "9186", 
            "Content-Type": "application/json", 
            "Host": "batch.upsight-api.com", 
            "User-Agent": "Android-24", 
            "X-US-Ref-Id": "ecdaa8e2-3dff-4557-815f-c5da8c953015"
        }, 
        "host": "batch.upsight-api.com", 
        "is_foreground": true, 
        "is_host_ip": 0, 
        "label": 0, 
        "md5": null, 
        "method": "POST", 
        "package_name": "com.nianticlabs.pokemongo", 
        "package_version": "0.57.4", 
        "pii_types": null, 
        "platform": "android", 
        "post_body": null, 
        "protocol": "HTTPS", 
        "referrer": null, 
        "scr_port": 39426, 
        "src_ip": "-", 
        "tk_flag": null, 
        "ts": "1488840253304", 
        "uri": "/batch/v1/a9cc12f87adc420baf964f187672ecb4/", 
        "user_agent": "Android-24"
    }, 
    "1488840313663,dc1018e5-2c63-486b-8d88-7e6963960e9c": {
        "domain": "", 
        "dst_ip": "169.46.12.93", 
        "dst_port": 443, 
        "headers": {
            "Accept-Encoding": "gzip", 
            "Connection": "close", 
            "Content-Length": "9186", 
            "Content-Type": "application/json", 
            "Host": "batch.upsight-api.com", 
            "User-Agent": "Android-24", 
            "X-US-Ref-Id": "d47595e3-3a6b-41db-a262-28775d32b2a2"
        }, 
        "host": "batch.upsight-api.com", 
        "is_foreground": false, 
        "is_host_ip": 0, 
        "label": 0, 
        "md5": null, 
        "method": "POST", 
        "package_name": "com.nianticlabs.pokemongo", 
        "package_version": "0.57.4", 
        "pii_types": null, 
        "platform": "android", 
        "post_body": null, 
        "protocol": "HTTPS", 
        "referrer": null, 
        "scr_port": 39432, 
        "src_ip": "-", 
        "tk_flag": null, 
        "ts": "1488840313663", 
        "uri": "/batch/v1/a9cc12f87adc420baf964f187672ecb4/", 
        "user_agent": "Android-24"
    }, 
    "1488840374190,d612ec9e-35b3-4a52-9de8-a3ab177c901d": {
        "domain": "", 
        "dst_ip": "169.46.12.74", 
        "dst_port": 443, 
        "headers": {
            "Accept-Encoding": "gzip", 
            "Connection": "close", 
            "Content-Length": "9186", 
            "Content-Type": "application/json", 
            "Host": "batch.upsight-api.com", 
            "User-Agent": "Android-24", 
            "X-US-Ref-Id": "706f2305-e95a-47f0-90c8-137ad8d9ea14"
        }, 
        "host": "batch.upsight-api.com", 
        "is_foreground": false, 
        "is_host_ip": 0, 
        "label": 0, 
        "md5": null, 
        "method": "POST", 
        "package_name": "com.nianticlabs.pokemongo", 
        "package_version": "0.57.4", 
        "pii_types": null, 
        "platform": "android", 
        "post_body": null, 
        "protocol": "HTTPS", 
        "referrer": null, 
        "scr_port": 43941, 
        "src_ip": "-", 
        "tk_flag": null, 
        "ts": "1488840374190", 
        "uri": "/batch/v1/a9cc12f87adc420baf964f187672ecb4/", 
        "user_agent": "Android-24"
    }, 
    "1488840410657,0e58555d-3b6c-4b92-8552-3574eadda6e6": {
        "domain": "", 
        "dst_ip": "169.46.12.74", 
        "dst_port": 443, 
        "headers": {
            "Accept-Encoding": "gzip", 
            "Connection": "close", 
            "Content-Length": "3339", 
            "Content-Type": "application/json", 
            "Host": "batch.upsight-api.com", 
            "User-Agent": "Android-24", 
            "X-US-Ref-Id": "a68457c1-8e94-46b3-bfe7-13149ced621c"
        }, 
        "host": "batch.upsight-api.com", 
        "is_foreground": false, 
        "is_host_ip": 0, 
        "label": 1, 
        "md5": null, 
        "method": "POST", 
        "package_name": "com.nianticlabs.pokemongo", 
        "package_version": "0.57.4", 
        "pii_types": [
            "AndroidId", 
            "Location"
        ], 
        "platform": "android", 
        "post_body": "[{\"app.version\":\"0.57.4\",\"app.token\":\"a9cc12f87adc420baf964f187672ecb4\",\"opt_out\":false,\"sid\":\"2360887839511745659\",\"identifiers\":\"pub\",\"device.os_version\":\"7.0 24\",\"device.carrier\":\"T-Mobile\",\"request_ts\":1488840410,\"device.limit_ad_tracking\":false,\"device.manufacturer\":\"motorola\",\"device.type\":\"phone\",\"bundle.schema_hash\":\"97d170e1550eee4afc0af065b78cda302a97674c\",\"sdk.version\":\"4.2.5\",\"device.jailbroken\":false,\"locale\":\"en_US\",\"device.hardware\":\"Nexus 6\",\"screen.scale\":1.0,\"device.connection\":\"WIFI\",\"screen.dpi\":560,\"location.lat\":\"RECON_Location64\",\"sessions\":[{\"session_start\":1488840130,\"install_ts\":1488840130,\"past_session_time\":0,\"session_num\":1,\"events\":[{\"user_attributes\":{\"player_avatar\":0,\"item_count\":54,\"player_level\":1,\"pokecoin\":0,\"player_xp\":0,\"pokemon_count\":0},\"pub_data\":{\"miss_percent\":\"0\",\"curve\":\"False\",\"status\":\"CATCH_MISSED\",\"balltype\":\"ITEM_POKE_BALL\",\"height\":\"0\",\"hit\":\"Miss\",\"map_pokemon_type\":\"StarterMapPokemon\",\"weight\":\"0\",\"pokemon_id\":\"4\",\"cp\":\"10\"},\"seq_id\":40,\"ts\":1488840343,\"type\":\"pub.action.catch_pokemon\",\"upsight_data\":{}},{\"user_attributes\":{\"player_avatar\":0,\"item_count\":54,\"player_level\":1,\"pokecoin\":0,\"player_xp\":0,\"pokemon_count\":0},\"pub_data\":{\"miss_percent\":\"0\",\"curve\":\"False\",\"status\":\"CATCH_SUCCESS\",\"balltype\":\"ITEM_POKE_BALL\",\"height\":\"0\",\"hit\":\"Normal\",\"map_pokemon_type\":\"StarterMapPokemon\",\"weight\":\"0\",\"pokemon_id\":\"4\",\"cp\":\"10\"},\"seq_id\":41,\"ts\":1488840355,\"type\":\"pub.action.catch_pokemon\",\"upsight_data\":{}},{\"user_attributes\":{\"player_avatar\":0,\"item_count\":54,\"player_level\":1,\"pokecoin\":0,\"player_xp\":0,\"pokemon_count\":0},\"pub_data\":{\"miss_percent\":\"0\",\"curve\":\"False\",\"status\":\"CATCH_MISSED\",\"balltype\":\"ITEM_POKE_BALL\",\"height\":\"0\",\"hit\":\"Miss\",\"map_pokemon_type\":\"StarterMapPokemon\",\"weight\":\"0\",\"pokemon_id\":\"4\",\"cp\":\"10\"},\"seq_id\":39,\"ts\":1488840331,\"type\":\"pub.action.catch_pokemon\",\"upsight_data\":{}},{\"user_attributes\":{\"player_avatar\":0,\"item_count\":54,\"player_level\":1,\"pokecoin\":0,\"player_xp\":0,\"pokemon_count\":0},\"pub_data\":{\"miss_percent\":\"0\",\"curve\":\"False\",\"status\":\"CATCH_MISSED\",\"balltype\":\"ITEM_POKE_BALL\",\"height\":\"0\",\"hit\":\"Miss\",\"map_pokemon_type\":\"StarterMapPokemon\",\"weight\":\"0\",\"pokemon_id\":\"4\",\"cp\":\"10\"},\"seq_id\":38,\"ts\":1488840327,\"type\":\"pub.action.catch_pokemon\",\"upsight_data\":{}},{\"user_attributes\":{\"player_avatar\":0,\"item_count\":54,\"player_level\":1,\"pokecoin\":0,\"player_xp\":0,\"pokemon_count\":0},\"pub_data\":{\"miss_percent\":\"0\",\"curve\":\"False\",\"status\":\"CATCH_MISSED\",\"balltype\":\"ITEM_POKE_BALL\",\"height\":\"0\",\"hit\":\"Miss\",\"map_pokemon_type\":\"StarterMapPokemon\",\"weight\":\"0\",\"pokemon_id\":\"4\",\"cp\":\"10\"},\"seq_id\":36,\"ts\":1488840290,\"type\":\"pub.action.catch_pokemon\",\"upsight_data\":{}},{\"user_attributes\":{\"player_avatar\":0,\"item_count\":54,\"player_level\":1,\"pokecoin\":0,\"player_xp\":0,\"pokemon_count\":0},\"pub_data\":{\"miss_percent\":\"0\",\"curve\":\"False\",\"status\":\"CATCH_MISSED\",\"balltype\":\"ITEM_POKE_BALL\",\"height\":\"0\",\"hit\":\"Miss\",\"map_pokemon_type\":\"StarterMapPokemon\",\"weight\":\"0\",\"pokemon_id\":\"4\",\"cp\":\"10\"},\"seq_id\":37,\"ts\":1488840307,\"type\":\"pub.action.catch_pokemon\",\"upsight_data\":{}}]}],\"screen.width\":1440,\"screen.height\":2392,\"location.tz\":\"-0800\",\"sdk.build\":\"cb.6+release.b16eeaa\",\"sdk.plugin\":\"unity:4.2.5-cb.6\",\"device.os\":\"android\",\"ids.android_id\":\"RECON_AndroidId\",\"app.bundleid\":\"com.nianticlabs.pokemongo\",\"location.lon\":\"RECON_Location84\"}]", 
        "protocol": "HTTPS", 
        "referrer": null, 
        "scr_port": 43948, 
        "src_ip": "-", 
        "tk_flag": null, 
        "ts": "1488840410657", 
        "uri": "/batch/v1/a9cc12f87adc420baf964f187672ecb4/", 
        "user_agent": "Android-24"
    }, 
    "1488840434445,c2bd5fdd-cc33-40da-83a6-1aa1a40fdbe6": {
        "domain": "", 
        "dst_ip": "169.46.12.74", 
        "dst_port": 443, 
        "headers": {
            "Accept-Encoding": "gzip", 
            "Connection": "close", 
            "Content-Length": "9186", 
            "Content-Type": "application/json", 
            "Host": "batch.upsight-api.com", 
            "User-Agent": "Android-24", 
            "X-US-Ref-Id": "11ad8c6d-ae91-4d5d-8b3b-2b65d507fc4e"
        }, 
        "host": "batch.upsight-api.com", 
        "is_foreground": true, 
        "is_host_ip": 0, 
        "label": 0, 
        "md5": null, 
        "method": "POST", 
        "package_name": "com.nianticlabs.pokemongo", 
        "package_version": "0.57.4", 
        "pii_types": null, 
        "platform": "android", 
        "post_body": null, 
        "protocol": "HTTPS", 
        "referrer": null, 
        "scr_port": 43952, 
        "src_ip": "-", 
        "tk_flag": null, 
        "ts": "1488840434445", 
        "uri": "/batch/v1/a9cc12f87adc420baf964f187672ecb4/", 
        "user_agent": "Android-24"
    }, 
    "1488840444552,f9a95755-e755-441a-bbd4-8206069bb00f": {
        "domain": "", 
        "dst_ip": "169.44.145.209", 
        "dst_port": 443, 
        "headers": {
            "Accept-Encoding": "gzip", 
            "Connection": "close", 
            "Content-Length": "1087", 
            "Content-Type": "application/json", 
            "Host": "bootstrap.upsight-api.com", 
            "User-Agent": "Android-24", 
            "X-US-Ref-Id": "f60c503e-8270-4293-8db9-d5f77a95211d"
        }, 
        "host": "bootstrap.upsight-api.com", 
        "is_foreground": true, 
        "is_host_ip": 0, 
        "label": 1, 
        "md5": null, 
        "method": "POST", 
        "package_name": "com.nianticlabs.pokemongo", 
        "package_version": "0.57.4", 
        "pii_types": [
            "AndroidId", 
            "Location"
        ], 
        "platform": "android", 
        "post_body": "[{\"app.version\":\"0.57.4\",\"app.token\":\"a9cc12f87adc420baf964f187672ecb4\",\"opt_out\":false,\"sid\":\"2360887839511745659\",\"identifiers\":\"pub\",\"device.os_version\":\"7.0 24\",\"device.carrier\":\"T-Mobile\",\"request_ts\":1488840444,\"device.limit_ad_tracking\":false,\"device.manufacturer\":\"motorola\",\"device.type\":\"phone\",\"bundle.schema_hash\":\"97d170e1550eee4afc0af065b78cda302a97674c\",\"sdk.version\":\"4.2.5\",\"device.jailbroken\":false,\"locale\":\"en_US\",\"device.hardware\":\"Nexus 6\",\"screen.scale\":1.0,\"device.connection\":\"WIFI\",\"screen.dpi\":560,\"location.lat\":\"RECON_Location64\",\"sessions\":[{\"install_ts\":1488840130,\"past_session_time\":0,\"events\":[{\"user_attributes\":{\"player_avatar\":0,\"item_count\":54,\"player_level\":1,\"pokecoin\":0,\"player_xp\":600,\"pokemon_count\":0},\"pub_data\":{},\"seq_id\":43,\"ts\":1488840444,\"type\":\"upsight.config.expired\",\"upsight_data\":{}}]}],\"screen.width\":1440,\"screen.height\":2392,\"location.tz\":\"-0800\",\"sdk.build\":\"cb.6+release.b16eeaa\",\"sdk.plugin\":\"unity:4.2.5-cb.6\",\"device.os\":\"android\",\"ids.android_id\":\"RECON_AndroidId\",\"app.bundleid\":\"com.nianticlabs.pokemongo\",\"location.lon\":\"RECON_Location84\"}]", 
        "protocol": "HTTPS", 
        "referrer": null, 
        "scr_port": 37863, 
        "src_ip": "-", 
        "tk_flag": null, 
        "ts": "1488840444552", 
        "uri": "/config/v1/a9cc12f87adc420baf964f187672ecb4/", 
        "user_agent": "Android-24"
    }, 
    "1488840495030,ac739ba3-4933-4840-bfa2-e49695cedc70": {
        "domain": "", 
        "dst_ip": "169.46.12.69", 
        "dst_port": 443, 
        "headers": {
            "Accept-Encoding": "gzip", 
            "Connection": "close", 
            "Content-Length": "9186", 
            "Content-Type": "application/json", 
            "Host": "batch.upsight-api.com", 
            "User-Agent": "Android-24", 
            "X-US-Ref-Id": "1a41003a-19cd-45c1-843e-b0a741570d02"
        }, 
        "host": "batch.upsight-api.com", 
        "is_foreground": false, 
        "is_host_ip": 0, 
        "label": 0, 
        "md5": null, 
        "method": "POST", 
        "package_name": "com.nianticlabs.pokemongo", 
        "package_version": "0.57.4", 
        "pii_types": null, 
        "platform": "android", 
        "post_body": null, 
        "protocol": "HTTPS", 
        "referrer": null, 
        "scr_port": 47184, 
        "src_ip": "-", 
        "tk_flag": null, 
        "ts": "1488840495030", 
        "uri": "/batch/v1/a9cc12f87adc420baf964f187672ecb4/", 
        "user_agent": "Android-24"
    }, 
    "1488840555483,5d98ea1b-d110-4a90-9cfe-b74eb04b5ffd": {
        "domain": "", 
        "dst_ip": "169.46.12.69", 
        "dst_port": 443, 
        "headers": {
            "Accept-Encoding": "gzip", 
            "Connection": "close", 
            "Content-Length": "9186", 
            "Content-Type": "application/json", 
            "Host": "batch.upsight-api.com", 
            "User-Agent": "Android-24", 
            "X-US-Ref-Id": "785ee2f9-e439-4c2a-890c-1e1250ef734b"
        }, 
        "host": "batch.upsight-api.com", 
        "is_foreground": false, 
        "is_host_ip": 0, 
        "label": 0, 
        "md5": null, 
        "method": "POST", 
        "package_name": "com.nianticlabs.pokemongo", 
        "package_version": "0.57.4", 
        "pii_types": null, 
        "platform": "android", 
        "post_body": null, 
        "protocol": "HTTPS", 
        "referrer": null, 
        "scr_port": 47199, 
        "src_ip": "-", 
        "tk_flag": null, 
        "ts": "1488840555483", 
        "uri": "/batch/v1/a9cc12f87adc420baf964f187672ecb4/", 
        "user_agent": "Android-24"
    }, 
    "1488840563936,8f7722cf-aaba-4357-8ae9-ce288abbafd1": {
        "domain": "", 
        "dst_ip": "169.46.12.69", 
        "dst_port": 443, 
        "headers": {
            "Accept-Encoding": "gzip", 
            "Connection": "close", 
            "Content-Length": "1564", 
            "Content-Type": "application/json", 
            "Host": "batch.upsight-api.com", 
            "User-Agent": "Android-24", 
            "X-US-Ref-Id": "8486ba80-0073-45c2-b7ae-6b5ecdcd35f7"
        }, 
        "host": "batch.upsight-api.com", 
        "is_foreground": false, 
        "is_host_ip": 0, 
        "label": 1, 
        "md5": null, 
        "method": "POST", 
        "package_name": "com.nianticlabs.pokemongo", 
        "package_version": "0.57.4", 
        "pii_types": [
            "AndroidId", 
            "Location"
        ], 
        "platform": "android", 
        "post_body": "[{\"app.version\":\"0.57.4\",\"app.token\":\"a9cc12f87adc420baf964f187672ecb4\",\"opt_out\":false,\"sid\":\"2360887839511745659\",\"identifiers\":\"pub\",\"device.os_version\":\"7.0 24\",\"device.carrier\":\"T-Mobile\",\"request_ts\":1488840563,\"device.limit_ad_tracking\":false,\"device.manufacturer\":\"motorola\",\"device.type\":\"phone\",\"bundle.schema_hash\":\"97d170e1550eee4afc0af065b78cda302a97674c\",\"sdk.version\":\"4.2.5\",\"device.jailbroken\":false,\"locale\":\"en_US\",\"device.hardware\":\"Nexus 6\",\"screen.scale\":1.0,\"device.connection\":\"WIFI\",\"screen.dpi\":560,\"location.lat\":\"RECON_Location64\",\"sessions\":[{\"session_start\":1488840130,\"install_ts\":1488840130,\"past_session_time\":0,\"session_num\":1,\"events\":[{\"user_attributes\":{\"player_avatar\":0,\"item_count\":54,\"player_level\":1,\"pokecoin\":0,\"player_xp\":600,\"pokemon_count\":0},\"pub_data\":{},\"seq_id\":45,\"ts\":1488840480,\"type\":\"upsight.session.pause\",\"upsight_data\":{}},{\"user_attributes\":{\"player_avatar\":0,\"item_count\":54,\"player_level\":1,\"pokecoin\":0,\"player_xp\":600,\"pokemon_count\":0},\"pub_data\":{},\"seq_id\":42,\"ts\":1488840443,\"type\":\"pub.usage.map.click_profile\",\"upsight_data\":{}},{\"user_attributes\":{\"player_avatar\":0,\"item_count\":54,\"player_level\":1,\"pokecoin\":0,\"player_xp\":600,\"pokemon_count\":0},\"pub_data\":{},\"seq_id\":44,\"ts\":1488840447,\"type\":\"pub.usage.profile.click_shop\",\"upsight_data\":{}}]}],\"screen.width\":1440,\"screen.height\":2392,\"location.tz\":\"-0800\",\"sdk.build\":\"cb.6+release.b16eeaa\",\"sdk.plugin\":\"unity:4.2.5-cb.6\",\"device.os\":\"android\",\"ids.android_id\":\"RECON_AndroidId\",\"app.bundleid\":\"com.nianticlabs.pokemongo\",\"location.lon\":\"RECON_Location84\"}]", 
        "protocol": "HTTPS", 
        "referrer": null, 
        "scr_port": 47201, 
        "src_ip": "-", 
        "tk_flag": null, 
        "ts": "1488840563936", 
        "uri": "/batch/v1/a9cc12f87adc420baf964f187672ecb4/", 
        "user_agent": "Android-24"
    }, 
    "1488840616231,f70fee73-526c-452e-8655-ec16ae092f08": {
        "domain": "", 
        "dst_ip": "169.46.12.84", 
        "dst_port": 443, 
        "headers": {
            "Accept-Encoding": "gzip", 
            "Connection": "close", 
            "Content-Length": "9186", 
            "Content-Type": "application/json", 
            "Host": "batch.upsight-api.com", 
            "User-Agent": "Android-24", 
            "X-US-Ref-Id": "b8e49402-2c61-43a4-b208-6ef95e0b0274"
        }, 
        "host": "batch.upsight-api.com", 
        "is_foreground": false, 
        "is_host_ip": 0, 
        "label": 0, 
        "md5": null, 
        "method": "POST", 
        "package_name": "com.nianticlabs.pokemongo", 
        "package_version": "0.57.4", 
        "pii_types": null, 
        "platform": "android", 
        "post_body": null, 
        "protocol": "HTTPS", 
        "referrer": null, 
        "scr_port": 48894, 
        "src_ip": "-", 
        "tk_flag": null, 
        "ts": "1488840616231", 
        "uri": "/batch/v1/a9cc12f87adc420baf964f187672ecb4/", 
        "user_agent": "Android-24"
    }, 
    "1488840676581,d3678237-b333-47d5-b79e-5a815efeea17": {
        "domain": "", 
        "dst_ip": "169.46.12.84", 
        "dst_port": 443, 
        "headers": {
            "Accept-Encoding": "gzip", 
            "Connection": "close", 
            "Content-Length": "9186", 
            "Content-Type": "application/json", 
            "Host": "batch.upsight-api.com", 
            "User-Agent": "Android-24", 
            "X-US-Ref-Id": "85d6dec0-4cef-4c8e-8475-82cdce5e82f6"
        }, 
        "host": "batch.upsight-api.com", 
        "is_foreground": false, 
        "is_host_ip": 0, 
        "label": 0, 
        "md5": null, 
        "method": "POST", 
        "package_name": "com.nianticlabs.pokemongo", 
        "package_version": "0.57.4", 
        "pii_types": null, 
        "platform": "android", 
        "post_body": null, 
        "protocol": "HTTPS", 
        "referrer": null, 
        "scr_port": 48897, 
        "src_ip": "-", 
        "tk_flag": null, 
        "ts": "1488840676581", 
        "uri": "/batch/v1/a9cc12f87adc420baf964f187672ecb4/", 
        "user_agent": "Android-24"
    }, 
    "1488840737268,7ea147e8-a05c-477e-a1e3-1dd0f412f849": {
        "domain": "", 
        "dst_ip": "169.46.12.88", 
        "dst_port": 443, 
        "headers": {
            "Accept-Encoding": "gzip", 
            "Connection": "close", 
            "Content-Length": "9186", 
            "Content-Type": "application/json", 
            "Host": "batch.upsight-api.com", 
            "User-Agent": "Android-24", 
            "X-US-Ref-Id": "0fb864a5-a412-4905-9e93-1e75527cb1af"
        }, 
        "host": "batch.upsight-api.com", 
        "is_foreground": false, 
        "is_host_ip": 0, 
        "label": 0, 
        "md5": null, 
        "method": "POST", 
        "package_name": "com.nianticlabs.pokemongo", 
        "package_version": "0.57.4", 
        "pii_types": null, 
        "platform": "android", 
        "post_body": null, 
        "protocol": "HTTPS", 
        "referrer": null, 
        "scr_port": 49561, 
        "src_ip": "-", 
        "tk_flag": null, 
        "ts": "1488840737268", 
        "uri": "/batch/v1/a9cc12f87adc420baf964f187672ecb4/", 
        "user_agent": "Android-24"
    }, 
    "1488840755604,93f454ec-d544-4a6d-bac9-10703ecd1eec": {
        "domain": "", 
        "dst_ip": "169.44.145.213", 
        "dst_port": 443, 
        "headers": {
            "Accept-Encoding": "gzip", 
            "Connection": "close", 
            "Content-Length": "1087", 
            "Content-Type": "application/json", 
            "Host": "bootstrap.upsight-api.com", 
            "User-Agent": "Android-24", 
            "X-US-Ref-Id": "37209f16-890e-4c3e-8ea8-f151362e10ed"
        }, 
        "host": "bootstrap.upsight-api.com", 
        "is_foreground": false, 
        "is_host_ip": 0, 
        "label": 1, 
        "md5": null, 
        "method": "POST", 
        "package_name": "com.nianticlabs.pokemongo", 
        "package_version": "0.57.4", 
        "pii_types": [
            "AndroidId", 
            "Location"
        ], 
        "platform": "android", 
        "post_body": "[{\"app.version\":\"0.57.4\",\"app.token\":\"a9cc12f87adc420baf964f187672ecb4\",\"opt_out\":false,\"sid\":\"2360887839511745659\",\"identifiers\":\"pub\",\"device.os_version\":\"7.0 24\",\"device.carrier\":\"T-Mobile\",\"request_ts\":1488840755,\"device.limit_ad_tracking\":false,\"device.manufacturer\":\"motorola\",\"device.type\":\"phone\",\"bundle.schema_hash\":\"97d170e1550eee4afc0af065b78cda302a97674c\",\"sdk.version\":\"4.2.5\",\"device.jailbroken\":false,\"locale\":\"en_US\",\"device.hardware\":\"Nexus 6\",\"screen.scale\":1.0,\"device.connection\":\"WIFI\",\"screen.dpi\":560,\"location.lat\":\"RECON_Location64\",\"sessions\":[{\"install_ts\":1488840130,\"past_session_time\":0,\"events\":[{\"user_attributes\":{\"player_avatar\":0,\"item_count\":54,\"player_level\":1,\"pokecoin\":0,\"player_xp\":600,\"pokemon_count\":0},\"pub_data\":{},\"seq_id\":46,\"ts\":1488840755,\"type\":\"upsight.config.expired\",\"upsight_data\":{}}]}],\"screen.width\":1440,\"screen.height\":2392,\"location.tz\":\"-0800\",\"sdk.build\":\"cb.6+release.b16eeaa\",\"sdk.plugin\":\"unity:4.2.5-cb.6\",\"device.os\":\"android\",\"ids.android_id\":\"RECON_AndroidId\",\"app.bundleid\":\"com.nianticlabs.pokemongo\",\"location.lon\":\"RECON_Location84\"}]", 
        "protocol": "HTTPS", 
        "referrer": null, 
        "scr_port": 43142, 
        "src_ip": "-", 
        "tk_flag": null, 
        "ts": "1488840755604", 
        "uri": "/config/v1/a9cc12f87adc420baf964f187672ecb4/", 
        "user_agent": "Android-24"
    }
}